[
    {
        "left": [
            {
                "position": {
                    "x": 0.0024231532588601112,
                    "y": -0.00528493570163846,
                    "z": 0.06514875590801239
                },
                "rotation": {
                    "x": 0.0,
                    "y": 0.0,
                    "z": 0.0,
                    "w": 0.9999998807907104
                }
            },
            {
                "position": {
                    "x": 0.0,
                    "y": 0.0,
                    "z": 0.0
                },
                "rotation": {
                    "x": 0.0,
                    "y": 0.0,
                    "z": 0.0,
                    "w": 0.9999998807907104
                }
            },
            {
                "position": {
                    "x": 0.02923935279250145,
                    "y": -0.017600754275918007,
                    "z": 0.035228271037340164
                },
                "rotation": {
                    "x": -0.04088142514228821,
                    "y": 0.3832574486732483,
                    "z": -0.6000887751579285,
                    "w": 0.700953483581543
                }
            },
            {
                "position": {
                    "x": 0.048303499817848206,
                    "y": -0.03069254755973816,
                    "z": 0.05808112397789955
                },
                "rotation": {
                    "x": 0.119957335293293,
                    "y": 0.2047949731349945,
                    "z": -0.6090686321258545,
                    "w": 0.756772518157959
                }
            },
            {
                "position": {
                    "x": 0.05384021997451782,
                    "y": -0.04525835067033768,
                    "z": 0.08806703984737396
                },
                "rotation": {
                    "x": 0.24502252042293549,
                    "y": 0.15480083227157593,
                    "z": -0.6837106347084045,
                    "w": 0.6697315573692322
                }
            },
            {
                "position": {
                    "x": 0.05170691758394241,
                    "y": -0.05802774429321289,
                    "z": 0.10900986194610596
                },
                "rotation": {
                    "x": 0.24502252042293549,
                    "y": 0.15480083227157593,
                    "z": -0.6837106347084045,
                    "w": 0.6697315573692322
                }
            },
            {
                "position": {
                    "x": 0.019329804927110672,
                    "y": -0.010263677686452866,
                    "z": 0.03681338578462601
                },
                "rotation": {
                    "x": 0.0,
                    "y": 0.0,
                    "z": 0.0,
                    "w": 0.9999998807907104
                }
            },
            {
                "position": {
                    "x": 0.02355070412158966,
                    "y": -0.00731643196195364,
                    "z": 0.09599623084068298
                },
                "rotation": {
                    "x": 0.2783326804637909,
                    "y": 0.03843768313527107,
                    "z": -0.04730901122093201,
                    "w": 0.9585484266281128
                }
            },
            {
                "position": {
                    "x": 0.025346670299768448,
                    "y": -0.027692044153809547,
                    "z": 0.12793508172035217
                },
                "rotation": {
                    "x": 0.5744484663009644,
                    "y": 0.015263856388628483,
                    "z": -0.03171246126294136,
                    "w": 0.8177838325500488
                }
            },
            {
                "position": {
                    "x": 0.025067945942282677,
                    "y": -0.05055001378059387,
                    "z": 0.13618740439414978
                },
                "rotation": {
                    "x": 0.6831157803535461,
                    "y": -0.018293606117367744,
                    "z": -0.03312232345342636,
                    "w": 0.7293292284011841
                }
            },
            {
                "position": {
                    "x": 0.023188328370451927,
                    "y": -0.07271876186132431,
                    "z": 0.13869236409664154
                },
                "rotation": {
                    "x": 0.6831157803535461,
                    "y": -0.018293606117367744,
                    "z": -0.03312232345342636,
                    "w": 0.7293292284011841
                }
            },
            {
                "position": {
                    "x": 0.003120377892628312,
                    "y": -0.0080267284065485,
                    "z": 0.03465091437101364
                },
                "rotation": {
                    "x": 0.0,
                    "y": 0.0,
                    "z": 0.0,
                    "w": 0.9999998807907104
                }
            },
            {
                "position": {
                    "x": 0.0017259278101846576,
                    "y": -0.0025431415997445583,
                    "z": 0.09564660489559174
                },
                "rotation": {
                    "x": 0.2556685209274292,
                    "y": 0.006701471284031868,
                    "z": 0.0062928833067417145,
                    "w": 0.9667206406593323
                }
            },
            {
                "position": {
                    "x": 0.002420254983007908,
                    "y": -0.02375919185578823,
                    "z": 0.13295778632164001
                },
                "rotation": {
                    "x": 0.5188968777656555,
                    "y": 0.004022084176540375,
                    "z": 0.016067631542682648,
                    "w": 0.854676365852356
                }
            },
            {
                "position": {
                    "x": 0.003069038735702634,
                    "y": -0.048191528767347336,
                    "z": 0.1456707864999771
                },
                "rotation": {
                    "x": 0.6141008138656616,
                    "y": -0.01866685040295124,
                    "z": 0.06458333134651184,
                    "w": 0.7863590717315674
                }
            },
            {
                "position": {
                    "x": 0.0038689374923706055,
                    "y": -0.07211726158857346,
                    "z": 0.15285088121891022
                },
                "rotation": {
                    "x": 0.6141008138656616,
                    "y": -0.01866685040295124,
                    "z": 0.06458333134651184,
                    "w": 0.7863590717315674
                }
            },
            {
                "position": {
                    "x": -0.014992338605225086,
                    "y": -0.006015794351696968,
                    "z": 0.03477553650736809
                },
                "rotation": {
                    "x": 0.0,
                    "y": 0.0,
                    "z": 0.0,
                    "w": 0.9999998807907104
                }
            },
            {
                "position": {
                    "x": -0.017465226352214813,
                    "y": -0.006529298145323992,
                    "z": 0.08869379013776779
                },
                "rotation": {
                    "x": 0.1246582418680191,
                    "y": -0.055189888924360275,
                    "z": 0.057169824838638306,
                    "w": 0.989012598991394
                }
            },
            {
                "position": {
                    "x": -0.021166516467928886,
                    "y": -0.016390955075621605,
                    "z": 0.12624035775661469
                },
                "rotation": {
                    "x": 0.47807830572128296,
                    "y": -0.025679372251033783,
                    "z": 0.11465458571910858,
                    "w": 0.8704227209091187
                }
            },
            {
                "position": {
                    "x": -0.019441235810518265,
                    "y": -0.03866340592503548,
                    "z": 0.1406315416097641
                },
                "rotation": {
                    "x": 0.638430655002594,
                    "y": 0.0169123075902462,
                    "z": 0.1437133550643921,
                    "w": 0.7559540867805481
                }
            },
            {
                "position": {
                    "x": -0.01491711288690567,
                    "y": -0.061856724321842194,
                    "z": 0.14663276076316833
                },
                "rotation": {
                    "x": 0.638430655002594,
                    "y": 0.0169123075902462,
                    "z": 0.1437133550643921,
                    "w": 0.7559540867805481
                }
            },
            {
                "position": {
                    "x": -0.022998588159680367,
                    "y": -0.009419853799045086,
                    "z": 0.03407356142997742
                },
                "rotation": {
                    "x": 0.01831180602312088,
                    "y": -0.1403428465127945,
                    "z": 0.20703598856925964,
                    "w": 0.9680414795875549
                }
            },
            {
                "position": {
                    "x": -0.03505405783653259,
                    "y": -0.013691171072423458,
                    "z": 0.07789584249258041
                },
                "rotation": {
                    "x": -0.05201292037963867,
                    "y": -0.16406317055225372,
                    "z": 0.09781759977340698,
                    "w": 0.9802089929580688
                }
            },
            {
                "position": {
                    "x": -0.04524732381105423,
                    "y": -0.011544717475771904,
                    "z": 0.1067962795495987
                },
                "rotation": {
                    "x": 0.4211263954639435,
                    "y": -0.10882829129695892,
                    "z": 0.24094028770923615,
                    "w": 0.8676154017448425
                }
            },
            {
                "position": {
                    "x": -0.04496114328503609,
                    "y": -0.027452489361166954,
                    "z": 0.11942216753959656
                },
                "rotation": {
                    "x": 0.623201310634613,
                    "y": 0.0003068074584007263,
                    "z": 0.2793196439743042,
                    "w": 0.7304796576499939
                }
            },
            {
                "position": {
                    "x": -0.03760692477226257,
                    "y": -0.047226034104824066,
                    "z": 0.12550923228263855
                },
                "rotation": {
                    "x": 0.623201310634613,
                    "y": 0.0003068074584007263,
                    "z": 0.2793196439743042,
                    "w": 0.7304796576499939
                }
            }
        ],
        "right": [
            {
                "position": {
                    "x": -0.00121830846183002,
                    "y": -0.005905368365347385,
                    "z": 0.06570760160684586
                },
                "rotation": {
                    "x": 0.0,
                    "y": 0.0,
                    "z": 0.0,
                    "w": 0.9999999403953552
                }
            },
            {
                "position": {
                    "x": 0.0,
                    "y": 0.0,
                    "z": 0.0
                },
                "rotation": {
                    "x": 0.0,
                    "y": 0.0,
                    "z": 0.0,
                    "w": 0.9999999403953552
                }
            },
            {
                "position": {
                    "x": -0.024419991299510002,
                    "y": -0.022564291954040527,
                    "z": 0.037463609129190445
                },
                "rotation": {
                    "x": 0.0852300301194191,
                    "y": -0.3585643172264099,
                    "z": 0.6860694289207458,
                    "w": 0.6272770762443542
                }
            },
            {
                "position": {
                    "x": -0.035243239253759384,
                    "y": -0.04203709959983826,
                    "z": 0.061143964529037476
                },
                "rotation": {
                    "x": 0.25218889117240906,
                    "y": -0.11985878646373749,
                    "z": 0.7083873748779297,
                    "w": 0.6482455134391785
                }
            },
            {
                "position": {
                    "x": -0.0284204613417387,
                    "y": -0.05882460996508598,
                    "z": 0.08966764807701111
                },
                "rotation": {
                    "x": 0.4463105797767639,
                    "y": 0.05502116680145264,
                    "z": 0.7480641007423401,
                    "w": 0.4880366921424866
                }
            },
            {
                "position": {
                    "x": -0.011463004164397717,
                    "y": -0.06752201914787292,
                    "z": 0.10525638610124588
                },
                "rotation": {
                    "x": 0.4463105797767639,
                    "y": 0.05502116680145264,
                    "z": 0.7480641007423401,
                    "w": 0.4880366921424866
                }
            },
            {
                "position": {
                    "x": -0.016920138150453568,
                    "y": -0.012745430693030357,
                    "z": 0.03793103247880936
                },
                "rotation": {
                    "x": 0.0,
                    "y": 0.0,
                    "z": 0.0,
                    "w": 0.9999999403953552
                }
            },
            {
                "position": {
                    "x": -0.023550692945718765,
                    "y": -0.007316436152905226,
                    "z": 0.09599619358778
                },
                "rotation": {
                    "x": 0.21295930445194244,
                    "y": 0.06145782768726349,
                    "z": 0.026159919798374176,
                    "w": 0.9747751951217651
                }
            },
            {
                "position": {
                    "x": -0.018583837896585464,
                    "y": -0.022940948605537415,
                    "z": 0.13019691407680511
                },
                "rotation": {
                    "x": 0.9012037515640259,
                    "y": 0.04675857350230217,
                    "z": -0.0555187463760376,
                    "w": 0.42727401852607727
                }
            },
            {
                "position": {
                    "x": -0.020044732838869095,
                    "y": -0.041783906519412994,
                    "z": 0.11491703242063522
                },
                "rotation": {
                    "x": 0.9898677468299866,
                    "y": 0.030436575412750244,
                    "z": -0.06703132390975952,
                    "w": -0.12141816318035126
                }
            },
            {
                "position": {
                    "x": -0.02284025028347969,
                    "y": -0.03746986389160156,
                    "z": 0.09312625974416733
                },
                "rotation": {
                    "x": 0.9898677468299866,
                    "y": 0.030436575412750244,
                    "z": -0.06703132390975952,
                    "w": -0.12141816318035126
                }
            },
            {
                "position": {
                    "x": -0.000710709486156702,
                    "y": -0.009267603978514671,
                    "z": 0.03576861694455147
                },
                "rotation": {
                    "x": 0.0,
                    "y": 0.0,
                    "z": 0.0,
                    "w": 0.9999999403953552
                }
            },
            {
                "position": {
                    "x": -0.001725906622596085,
                    "y": -0.0025431320536881685,
                    "z": 0.09564659744501114
                },
                "rotation": {
                    "x": 0.4355250895023346,
                    "y": 0.07410017400979996,
                    "z": -0.03938012570142746,
                    "w": 0.8962566256523132
                }
            },
            {
                "position": {
                    "x": 0.0025034043937921524,
                    "y": -0.03630610927939415,
                    "z": 0.1218171939253807
                },
                "rotation": {
                    "x": 0.969463586807251,
                    "y": 0.01588357239961624,
                    "z": -0.095802441239357,
                    "w": 0.22518828511238098
                }
            },
            {
                "position": {
                    "x": -0.002416955539956689,
                    "y": -0.04841877520084381,
                    "z": 0.0975673645734787
                },
                "rotation": {
                    "x": 0.9165385961532593,
                    "y": 0.041741710156202316,
                    "z": -0.13155394792556763,
                    "w": -0.37537750601768494
                }
            },
            {
                "position": {
                    "x": -0.00894797220826149,
                    "y": -0.032273415476083755,
                    "z": 0.07964234799146652
                },
                "rotation": {
                    "x": 0.9165385961532593,
                    "y": 0.041741710156202316,
                    "z": -0.13155394792556763,
                    "w": -0.37537750601768494
                }
            },
            {
                "position": {
                    "x": 0.014992328360676765,
                    "y": -0.006015765480697155,
                    "z": 0.034775517880916595
                },
                "rotation": {
                    "x": 0.0,
                    "y": 0.0,
                    "z": 0.0,
                    "w": 0.9999999403953552
                }
            },
            {
                "position": {
                    "x": 0.01746523007750511,
                    "y": -0.006529313512146473,
                    "z": 0.08869373798370361
                },
                "rotation": {
                    "x": 0.5223434567451477,
                    "y": 0.07394494116306305,
                    "z": -0.09751876443624496,
                    "w": 0.8439072966575623
                }
            },
            {
                "position": {
                    "x": 0.018359366804361343,
                    "y": -0.04147140309214592,
                    "z": 0.10598386079072952
                },
                "rotation": {
                    "x": 0.9709808230400085,
                    "y": -0.021340034902095795,
                    "z": -0.16670237481594086,
                    "w": 0.17015105485916138
                }
            },
            {
                "position": {
                    "x": 0.009563803672790527,
                    "y": -0.0500628836452961,
                    "z": 0.08242607116699219
                },
                "rotation": {
                    "x": 0.8960163593292236,
                    "y": -0.08609623461961746,
                    "z": -0.1575247198343277,
                    "w": -0.40611347556114197
                }
            },
            {
                "position": {
                    "x": 0.004185306373983622,
                    "y": -0.03275991603732109,
                    "z": 0.06611368060112
                },
                "rotation": {
                    "x": 0.8960163593292236,
                    "y": -0.08609623461961746,
                    "z": -0.1575247198343277,
                    "w": -0.40611347556114197
                }
            },
            {
                "position": {
                    "x": 0.022998569533228874,
                    "y": -0.009419817477464676,
                    "z": 0.03407353535294533
                },
                "rotation": {
                    "x": 0.018311744555830956,
                    "y": 0.14034277200698853,
                    "z": -0.20703595876693726,
                    "w": 0.9680414795875549
                }
            },
            {
                "position": {
                    "x": 0.03505405783653259,
                    "y": -0.013691157102584839,
                    "z": 0.0778958797454834
                },
                "rotation": {
                    "x": 0.5603041648864746,
                    "y": 0.019328981637954712,
                    "z": -0.17962899804115295,
                    "w": 0.8083432912826538
                }
            },
            {
                "position": {
                    "x": 0.029830213636159897,
                    "y": -0.04173216223716736,
                    "z": 0.08930447697639465
                },
                "rotation": {
                    "x": 0.9628257155418396,
                    "y": -0.06101278215646744,
                    "z": -0.21074455976486206,
                    "w": 0.1575775444507599
                }
            },
            {
                "position": {
                    "x": 0.02119687758386135,
                    "y": -0.04737310856580734,
                    "z": 0.07180602848529816
                },
                "rotation": {
                    "x": 0.8928864002227783,
                    "y": -0.1711576133966446,
                    "z": -0.1869480311870575,
                    "w": -0.3721684217453003
                }
            },
            {
                "position": {
                    "x": 0.015915323048830032,
                    "y": -0.03216729685664177,
                    "z": 0.05687218904495239
                },
                "rotation": {
                    "x": 0.8928864002227783,
                    "y": -0.1711576133966446,
                    "z": -0.1869480311870575,
                    "w": -0.3721684217453003
                }
            }
        ],
        "rootL": {
            "x": -0.17071151733398438,
            "y": 0.5869479179382324,
            "z": 0.2724683880805969
        },
        "rootR": {
            "x": 0.1546344757080078,
            "y": 0.9958871603012085,
            "z": 0.394325315952301
        },
        "RighthandRotation": {
            "x": -0.6500968933105469,
            "y": -0.16090437769889832,
            "z": -0.13174280524253845,
            "w": 0.7308403253555298
        },
        "LefthandRotation": {
            "x": 0.11168426275253296,
            "y": -0.12358152866363525,
            "z": -0.26543036103248596,
            "w": -0.949631929397583
        },
        "headPos": {
            "x": -0.016041938215494156,
            "y": 1.1501119136810303,
            "z": 0.14292147755622864
        },
        "headRot": {
            "x": -0.0377272330224514,
            "y": 0.04332702234387398,
            "z": 0.02628604881465435,
            "w": 0.998002290725708
        }
    },
    {
        "left": [
            {
                "position": {
                    "x": 0.0025427413638681173,
                    "y": -0.005196740385144949,
                    "z": 0.06506431847810745
                },
                "rotation": {
                    "x": 0.0,
                    "y": 0.0,
                    "z": 0.0,
                    "w": 1.0
                }
            },
            {
                "position": {
                    "x": 0.0,
                    "y": 0.0,
                    "z": 0.0
                },
                "rotation": {
                    "x": 0.0,
                    "y": 0.0,
                    "z": 0.0,
                    "w": 1.0
                }
            },
            {
                "position": {
                    "x": 0.02971775270998478,
                    "y": -0.016895033419132233,
                    "z": 0.034890539944171906
                },
                "rotation": {
                    "x": -0.051512449979782104,
                    "y": 0.39158520102500916,
                    "z": -0.5886901021003723,
                    "w": 0.7053024768829346
                }
            },
            {
                "position": {
                    "x": 0.04964887350797653,
                    "y": -0.029522420838475227,
                    "z": 0.057259902358055115
                },
                "rotation": {
                    "x": 0.10783903300762177,
                    "y": 0.2192777693271637,
                    "z": -0.5975580811500549,
                    "w": 0.7636834979057312
                }
            },
            {
                "position": {
                    "x": 0.056611526757478714,
                    "y": -0.043944358825683594,
                    "z": 0.08701729774475098
                },
                "rotation": {
                    "x": 0.24018485844135284,
                    "y": 0.1624041497707367,
                    "z": -0.6768980622291565,
                    "w": 0.6765689253807068
                }
            },
            {
                "position": {
                    "x": 0.0550195649266243,
                    "y": -0.05681392550468445,
                    "z": 0.10794694721698761
                },
                "rotation": {
                    "x": 0.24018485844135284,
                    "y": 0.1624041497707367,
                    "z": -0.6768980622291565,
                    "w": 0.6765689253807068
                }
            },
            {
                "position": {
                    "x": 0.019569018855690956,
                    "y": -0.009910782799124718,
                    "z": 0.03664453327655792
                },
                "rotation": {
                    "x": 0.0,
                    "y": 0.0,
                    "z": 0.0,
                    "w": 1.0
                }
            },
            {
                "position": {
                    "x": 0.023550689220428467,
                    "y": -0.007316436152905226,
                    "z": 0.09599625319242477
                },
                "rotation": {
                    "x": 0.28231507539749146,
                    "y": 0.046655334532260895,
                    "z": -0.04953180253505707,
                    "w": 0.9569056034088135
                }
            },
            {
                "position": {
                    "x": 0.02587646245956421,
                    "y": -0.027983779087662697,
                    "z": 0.1277126967906952
                },
                "rotation": {
                    "x": 0.5844016075134277,
                    "y": 0.02192750945687294,
                    "z": -0.03669978305697441,
                    "w": 0.8103377819061279
                }
            },
            {
                "position": {
                    "x": 0.025697626173496246,
                    "y": -0.05104151740670204,
                    "z": 0.13539238274097443
                },
                "rotation": {
                    "x": 0.6998311281204224,
                    "y": -0.012667717412114143,
                    "z": -0.03938481956720352,
                    "w": 0.7131093740463257
                }
            },
            {
                "position": {
                    "x": 0.02380564995110035,
                    "y": -0.07330068200826645,
                    "z": 0.1368781477212906
                },
                "rotation": {
                    "x": 0.6998311281204224,
                    "y": -0.012667717412114143,
                    "z": -0.03938481956720352,
                    "w": 0.7131093740463257
                }
            },
            {
                "position": {
                    "x": 0.003359574591740966,
                    "y": -0.007850310765206814,
                    "z": 0.03448205441236496
                },
                "rotation": {
                    "x": 0.0,
                    "y": 0.0,
                    "z": 0.0,
                    "w": 1.0
                }
            },
            {
                "position": {
                    "x": 0.001725889858789742,
                    "y": -0.002543175360187888,
                    "z": 0.09564662724733353
                },
                "rotation": {
                    "x": 0.24858634173870087,
                    "y": 0.01057329773902893,
                    "z": 0.005550311878323555,
                    "w": 0.9685362577438354
                }
            },
            {
                "position": {
                    "x": 0.002723564626649022,
                    "y": -0.0232087392359972,
                    "z": 0.133258655667305
                },
                "rotation": {
                    "x": 0.5195634365081787,
                    "y": 0.007718876004219055,
                    "z": 0.014242228120565414,
                    "w": 0.8542784452438354
                }
            },
            {
                "position": {
                    "x": 0.003494618460536003,
                    "y": -0.047658540308475494,
                    "z": 0.145931214094162
                },
                "rotation": {
                    "x": 0.6342483758926392,
                    "y": -0.015186646953225136,
                    "z": 0.06458955258131027,
                    "w": 0.7702770829200745
                }
            },
            {
                "position": {
                    "x": 0.0045149438083171844,
                    "y": -0.07191257923841476,
                    "z": 0.15187576413154602
                },
                "rotation": {
                    "x": 0.6342483758926392,
                    "y": -0.015186646953225136,
                    "z": 0.06458955258131027,
                    "w": 0.7702770829200745
                }
            },
            {
                "position": {
                    "x": -0.014992333017289639,
                    "y": -0.0060157873667776585,
                    "z": 0.03477555140852928
                },
                "rotation": {
                    "x": 0.0,
                    "y": 0.0,
                    "z": 0.0,
                    "w": 1.0
                }
            },
            {
                "position": {
                    "x": -0.01746523007750511,
                    "y": -0.0065292855724692345,
                    "z": 0.08869381248950958
                },
                "rotation": {
                    "x": 0.1148579865694046,
                    "y": -0.051952607929706573,
                    "z": 0.05645589530467987,
                    "w": 0.9904149174690247
                }
            },
            {
                "position": {
                    "x": -0.02097255364060402,
                    "y": -0.01563023217022419,
                    "z": 0.12645047903060913
                },
                "rotation": {
                    "x": 0.48450273275375366,
                    "y": -0.020777691155672073,
                    "z": 0.1134604662656784,
                    "w": 0.8671520352363586
                }
            },
            {
                "position": {
                    "x": -0.019008547067642212,
                    "y": -0.038084451109170914,
                    "z": 0.14052514731884003
                },
                "rotation": {
                    "x": 0.6669679880142212,
                    "y": 0.024116145446896553,
                    "z": 0.14274831116199493,
                    "w": 0.7308868169784546
                }
            },
            {
                "position": {
                    "x": -0.014049808494746685,
                    "y": -0.06158414110541344,
                    "z": 0.14471915364265442
                },
                "rotation": {
                    "x": 0.6669679880142212,
                    "y": 0.024116145446896553,
                    "z": 0.14274831116199493,
                    "w": 0.7308868169784546
                }
            },
            {
                "position": {
                    "x": -0.022998584434390068,
                    "y": -0.009419862180948257,
                    "z": 0.03407356142997742
                },
                "rotation": {
                    "x": 0.01831183210015297,
                    "y": -0.1403428316116333,
                    "z": 0.20703598856925964,
                    "w": 0.9680417776107788
                }
            },
            {
                "position": {
                    "x": -0.03505406156182289,
                    "y": -0.013691180385649204,
                    "z": 0.07789585739374161
                },
                "rotation": {
                    "x": -0.06057222560048103,
                    "y": -0.165312260389328,
                    "z": 0.09589049965143204,
                    "w": 0.9796979427337646
                }
            },
            {
                "position": {
                    "x": -0.045361652970314026,
                    "y": -0.011019088327884674,
                    "z": 0.10671178996562958
                },
                "rotation": {
                    "x": 0.43116340041160583,
                    "y": -0.10557910799980164,
                    "z": 0.24303261935710907,
                    "w": 0.8624885082244873
                }
            },
            {
                "position": {
                    "x": -0.044804077595472336,
                    "y": -0.027167966589331627,
                    "z": 0.11901850998401642
                },
                "rotation": {
                    "x": 0.6560099124908447,
                    "y": 0.012467116117477417,
                    "z": 0.2818063199520111,
                    "w": 0.700057864189148
                }
            },
            {
                "position": {
                    "x": -0.03656861558556557,
                    "y": -0.04707188904285431,
                    "z": 0.12327783554792404
                },
                "rotation": {
                    "x": 0.6560099124908447,
                    "y": 0.012467116117477417,
                    "z": 0.2818063199520111,
                    "w": 0.700057864189148
                }
            }
        ],
        "right": [
            {
                "position": {
                    "x": -0.000558580388315022,
                    "y": -0.006124584935605526,
                    "z": 0.06588253378868103
                },
                "rotation": {
                    "x": 0.0,
                    "y": 0.0,
                    "z": 0.0,
                    "w": 1.0000001192092896
                }
            },
            {
                "position": {
                    "x": 0.0,
                    "y": 0.0,
                    "z": 0.0
                },
                "rotation": {
                    "x": 0.0,
                    "y": 0.0,
                    "z": 0.0,
                    "w": 1.0000001192092896
                }
            },
            {
                "position": {
                    "x": -0.021781107410788536,
                    "y": -0.024317964911460876,
                    "z": 0.03816328942775726
                },
                "rotation": {
                    "x": 0.16131500899791718,
                    "y": -0.36005449295043945,
                    "z": 0.713860273361206,
                    "w": 0.578568696975708
                }
            },
            {
                "position": {
                    "x": -0.02783890813589096,
                    "y": -0.04710042476654053,
                    "z": 0.0605541430413723
                },
                "rotation": {
                    "x": 0.3305611312389374,
                    "y": -0.08424431085586548,
                    "z": 0.7475134134292603,
                    "w": 0.5699615478515625
                }
            },
            {
                "position": {
                    "x": -0.014383649453520775,
                    "y": -0.0640903115272522,
                    "z": 0.08648242056369781
                },
                "rotation": {
                    "x": 0.4870595932006836,
                    "y": 0.0669965147972107,
                    "z": 0.7709230780601501,
                    "w": 0.4049227833747864
                }
            },
            {
                "position": {
                    "x": 0.004710893612354994,
                    "y": -0.07146849483251572,
                    "z": 0.10016346722841263
                },
                "rotation": {
                    "x": 0.4870595932006836,
                    "y": 0.0669965147972107,
                    "z": 0.7709230780601501,
                    "w": 0.4049227833747864
                }
            },
            {
                "position": {
                    "x": -0.015600686892867088,
                    "y": -0.013622277416288853,
                    "z": 0.038280896842479706
                },
                "rotation": {
                    "x": 0.0,
                    "y": 0.0,
                    "z": 0.0,
                    "w": 1.0000001192092896
                }
            },
            {
                "position": {
                    "x": -0.02355068176984787,
                    "y": -0.007316447328776121,
                    "z": 0.09599627554416656
                },
                "rotation": {
                    "x": 0.49469149112701416,
                    "y": 0.024570317938923836,
                    "z": 0.03572118654847145,
                    "w": 0.8679866790771484
                }
            },
            {
                "position": {
                    "x": -0.020592527464032173,
                    "y": -0.03982078284025192,
                    "z": 0.11531464755535126
                },
                "rotation": {
                    "x": 0.9913319945335388,
                    "y": 0.038763150572776794,
                    "z": -0.02347356453537941,
                    "w": 0.12331847846508026
                }
            },
            {
                "position": {
                    "x": -0.021491270512342453,
                    "y": -0.04580722004175186,
                    "z": 0.09177698940038681
                },
                "rotation": {
                    "x": 0.8773621320724487,
                    "y": 0.0353739857673645,
                    "z": -0.03214723616838455,
                    "w": -0.4774422347545624
                }
            },
            {
                "position": {
                    "x": -0.023181751370429993,
                    "y": -0.027650248259305954,
                    "z": 0.07878752797842026
                },
                "rotation": {
                    "x": 0.8773621320724487,
                    "y": 0.0353739857673645,
                    "z": -0.03214723616838455,
                    "w": -0.4774422347545624
                }
            },
            {
                "position": {
                    "x": 0.0006087446236051619,
                    "y": -0.009706048294901848,
                    "z": 0.03611840307712555
                },
                "rotation": {
                    "x": 0.0,
                    "y": 0.0,
                    "z": 0.0,
                    "w": 1.0000001192092896
                }
            },
            {
                "position": {
                    "x": -0.0017259010346606374,
                    "y": -0.0025431460235267878,
                    "z": 0.09564666450023651
                },
                "rotation": {
                    "x": 0.5214148163795471,
                    "y": 0.04468509554862976,
                    "z": -0.032100748270750046,
                    "w": 0.8515278100967407
                }
            },
            {
                "position": {
                    "x": 0.00010386667418060824,
                    "y": -0.04078539460897446,
                    "z": 0.11506076902151108
                },
                "rotation": {
                    "x": 0.9803612232208252,
                    "y": 0.008019629865884781,
                    "z": -0.06797283887863159,
                    "w": 0.18495309352874756
                }
            },
            {
                "position": {
                    "x": -0.0034860980231314898,
                    "y": -0.05080607160925865,
                    "z": 0.08965051919221878
                },
                "rotation": {
                    "x": 0.9128482341766357,
                    "y": 0.05337752774357796,
                    "z": -0.10061705857515335,
                    "w": -0.39209118485450745
                }
            },
            {
                "position": {
                    "x": -0.00879528559744358,
                    "y": -0.03393006697297096,
                    "z": 0.0719970166683197
                },
                "rotation": {
                    "x": 0.9128482341766357,
                    "y": 0.05337752774357796,
                    "z": -0.10061705857515335,
                    "w": -0.39209118485450745
                }
            },
            {
                "position": {
                    "x": 0.01499233115464449,
                    "y": -0.0060157692059874535,
                    "z": 0.03477555140852928
                },
                "rotation": {
                    "x": 0.0,
                    "y": 0.0,
                    "z": 0.0,
                    "w": 1.0000001192092896
                }
            },
            {
                "position": {
                    "x": 0.017465239390730858,
                    "y": -0.006529307458549738,
                    "z": 0.08869382739067078
                },
                "rotation": {
                    "x": 0.5497708916664124,
                    "y": 0.06541123986244202,
                    "z": -0.09660157561302185,
                    "w": 0.8271284103393555
                }
            },
            {
                "position": {
                    "x": 0.017542822286486626,
                    "y": -0.042487651109695435,
                    "z": 0.10378319770097733
                },
                "rotation": {
                    "x": 0.9730960130691528,
                    "y": -0.02117215283215046,
                    "z": -0.16019295156002045,
                    "w": 0.16423861682415009
                }
            },
            {
                "position": {
                    "x": 0.009073326364159584,
                    "y": -0.05080128088593483,
                    "z": 0.08000726997852325
                },
                "rotation": {
                    "x": 0.9021380543708801,
                    "y": -0.08050748705863953,
                    "z": -0.154216930270195,
                    "w": -0.3948200047016144
                }
            },
            {
                "position": {
                    "x": 0.0036639063619077206,
                    "y": -0.03396020084619522,
                    "z": 0.06322842091321945
                },
                "rotation": {
                    "x": 0.9021380543708801,
                    "y": -0.08050748705863953,
                    "z": -0.154216930270195,
                    "w": -0.3948200047016144
                }
            },
            {
                "position": {
                    "x": 0.022998573258519173,
                    "y": -0.009419848211109638,
                    "z": 0.034073539078235626
                },
                "rotation": {
                    "x": 0.018311871215701103,
                    "y": 0.1403428614139557,
                    "z": -0.20703598856925964,
                    "w": 0.968041718006134
                }
            },
            {
                "position": {
                    "x": 0.03505406156182289,
                    "y": -0.013691195286810398,
                    "z": 0.07789580523967743
                },
                "rotation": {
                    "x": 0.5771865844726562,
                    "y": -0.0038405247032642365,
                    "z": -0.16852129995822906,
                    "w": 0.7990254759788513
                }
            },
            {
                "position": {
                    "x": 0.028889277949929237,
                    "y": -0.04198712855577469,
                    "z": 0.08814667910337448
                },
                "rotation": {
                    "x": 0.9727699756622314,
                    "y": -0.07074034214019775,
                    "z": -0.18448889255523682,
                    "w": 0.12115567922592163
                }
            },
            {
                "position": {
                    "x": 0.02125074900686741,
                    "y": -0.046244654804468155,
                    "z": 0.06981424242258072
                },
                "rotation": {
                    "x": 0.86920565366745,
                    "y": -0.16816191375255585,
                    "z": -0.15371227264404297,
                    "w": -0.43883517384529114
                }
            },
            {
                "position": {
                    "x": 0.017887845635414124,
                    "y": -0.02902735024690628,
                    "z": 0.05660867691040039
                },
                "rotation": {
                    "x": 0.86920565366745,
                    "y": -0.16816191375255585,
                    "z": -0.15371227264404297,
                    "w": -0.43883517384529114
                }
            }
        ],
        "rootL": {
            "x": -0.17030715942382812,
            "y": 0.5878766775131226,
            "z": 0.2746579051017761
        },
        "rootR": {
            "x": 0.14488434791564941,
            "y": 0.9648331999778748,
            "z": 0.45203137397766113
        },
        "RighthandRotation": {
            "x": -0.5902721881866455,
            "y": -0.11040976643562317,
            "z": -0.02982279658317566,
            "w": 0.7990614175796509
        },
        "LefthandRotation": {
            "x": 0.10231012850999832,
            "y": -0.12409758567810059,
            "z": -0.26491618156433105,
            "w": -0.9507638216018677
        },
        "headPos": {
            "x": -0.011637027375400066,
            "y": 1.151496410369873,
            "z": 0.11926955729722977
        },
        "headRot": {
            "x": -0.03770599141716957,
            "y": 0.041552841663360596,
            "z": 0.012181715108454227,
            "w": 0.9983502626419067
        }
    },
    {
        "left": [
            {
                "position": {
                    "x": 0.002628687070682645,
                    "y": -0.005128222052007914,
                    "z": 0.06499814242124557
                },
                "rotation": {
                    "x": 0.0,
                    "y": 0.0,
                    "z": 0.0,
                    "w": 1.0000001192092896
                }
            },
            {
                "position": {
                    "x": 0.0,
                    "y": 0.0,
                    "z": 0.0
                },
                "rotation": {
                    "x": 0.0,
                    "y": 0.0,
                    "z": 0.0,
                    "w": 1.0000001192092896
                }
            },
            {
                "position": {
                    "x": 0.03006151132285595,
                    "y": -0.01634712889790535,
                    "z": 0.03462568670511246
                },
                "rotation": {
                    "x": -0.05908390134572983,
                    "y": 0.39863166213035583,
                    "z": -0.5800660848617554,
                    "w": 0.707902193069458
                }
            },
            {
                "position": {
                    "x": 0.050639886409044266,
                    "y": -0.02866348996758461,
                    "z": 0.05657852813601494
                },
                "rotation": {
                    "x": 0.10649406164884567,
                    "y": 0.22506871819496155,
                    "z": -0.5917909145355225,
                    "w": 0.7666727304458618
                }
            },
            {
                "position": {
                    "x": 0.058042701333761215,
                    "y": -0.04318372160196304,
                    "z": 0.08618152141571045
                },
                "rotation": {
                    "x": 0.20938363671302795,
                    "y": 0.19788311421871185,
                    "z": -0.6671777963638306,
                    "w": 0.6869314908981323
                }
            },
            {
                "position": {
                    "x": 0.058862946927547455,
                    "y": -0.056169137358665466,
                    "z": 0.10708405822515488
                },
                "rotation": {
                    "x": 0.20938363671302795,
                    "y": 0.19788311421871185,
                    "z": -0.6671777963638306,
                    "w": 0.6869314908981323
                }
            },
            {
                "position": {
                    "x": 0.019740883260965347,
                    "y": -0.009636866860091686,
                    "z": 0.036512088030576706
                },
                "rotation": {
                    "x": 0.0,
                    "y": 0.0,
                    "z": 0.0,
                    "w": 1.0000001192092896
                }
            },
            {
                "position": {
                    "x": 0.023550676181912422,
                    "y": -0.00731647526845336,
                    "z": 0.09599625319242477
                },
                "rotation": {
                    "x": 0.3034437298774719,
                    "y": 0.043425053358078,
                    "z": -0.05062789469957352,
                    "w": 0.9505121111869812
                }
            },
            {
                "position": {
                    "x": 0.025516327470541,
                    "y": -0.029361719265580177,
                    "z": 0.12679599225521088
                },
                "rotation": {
                    "x": 0.6055235862731934,
                    "y": 0.017803434282541275,
                    "z": -0.03687692806124687,
                    "w": 0.794773519039154
                }
            },
            {
                "position": {
                    "x": 0.02511870488524437,
                    "y": -0.05278609320521355,
                    "z": 0.13326196372509003
                },
                "rotation": {
                    "x": 0.7186247110366821,
                    "y": -0.016779400408267975,
                    "z": -0.039688631892204285,
                    "w": 0.6940622329711914
                }
            },
            {
                "position": {
                    "x": 0.023059414699673653,
                    "y": -0.07507815212011337,
                    "z": 0.133548766374588
                },
                "rotation": {
                    "x": 0.7186247110366821,
                    "y": -0.016779400408267975,
                    "z": -0.039688631892204285,
                    "w": 0.6940622329711914
                }
            },
            {
                "position": {
                    "x": 0.0035314555279910564,
                    "y": -0.007713330909609795,
                    "z": 0.034349627792835236
                },
                "rotation": {
                    "x": 0.0,
                    "y": 0.0,
                    "z": 0.0,
                    "w": 1.0000001192092896
                }
            },
            {
                "position": {
                    "x": 0.0017259123269468546,
                    "y": -0.0025431597605347633,
                    "z": 0.09564661979675293
                },
                "rotation": {
                    "x": 0.2547444701194763,
                    "y": 0.009763475507497787,
                    "z": 0.005635455250740051,
                    "w": 0.9669429063796997
                }
            },
            {
                "position": {
                    "x": 0.0026596798561513424,
                    "y": -0.023686274886131287,
                    "z": 0.13299398124217987
                },
                "rotation": {
                    "x": 0.5314688682556152,
                    "y": 0.006995042786002159,
                    "z": 0.014493931084871292,
                    "w": 0.8469251394271851
                }
            },
            {
                "position": {
                    "x": 0.0034105421509593725,
                    "y": -0.04848159849643707,
                    "z": 0.1449776142835617
                },
                "rotation": {
                    "x": 0.6501548290252686,
                    "y": -0.0165739506483078,
                    "z": 0.06521168351173401,
                    "w": 0.7568169832229614
                }
            },
            {
                "position": {
                    "x": 0.004458526615053415,
                    "y": -0.07296112924814224,
                    "z": 0.1499062329530716
                },
                "rotation": {
                    "x": 0.6501548290252686,
                    "y": -0.0165739506483078,
                    "z": 0.06521168351173401,
                    "w": 0.7568169832229614
                }
            },
            {
                "position": {
                    "x": -0.014992336742579937,
                    "y": -0.006015782710164785,
                    "z": 0.03477556258440018
                },
                "rotation": {
                    "x": 0.0,
                    "y": 0.0,
                    "z": 0.0,
                    "w": 1.0000001192092896
                }
            },
            {
                "position": {
                    "x": -0.017465265467762947,
                    "y": -0.006529325619339943,
                    "z": 0.08869379013776779
                },
                "rotation": {
                    "x": 0.1235862672328949,
                    "y": -0.051335860043764114,
                    "z": 0.056827787309885025,
                    "w": 0.9893744587898254
                }
            },
            {
                "position": {
                    "x": -0.020878765732049942,
                    "y": -0.016293205320835114,
                    "z": 0.1262931525707245
                },
                "rotation": {
                    "x": 0.5009677410125732,
                    "y": -0.019379939883947372,
                    "z": 0.11401209235191345,
                    "w": 0.8577048778533936
                }
            },
            {
                "position": {
                    "x": -0.01872662827372551,
                    "y": -0.03924686089158058,
                    "z": 0.1395084261894226
                },
                "rotation": {
                    "x": 0.6856164932250977,
                    "y": 0.025681445375084877,
                    "z": 0.14350157976150513,
                    "w": 0.7132169008255005
                }
            },
            {
                "position": {
                    "x": -0.013568229973316193,
                    "y": -0.06289003044366837,
                    "z": 0.14247585833072662
                },
                "rotation": {
                    "x": 0.6856164932250977,
                    "y": 0.025681445375084877,
                    "z": 0.14350157976150513,
                    "w": 0.7132169008255005
                }
            },
            {
                "position": {
                    "x": -0.022998591884970665,
                    "y": -0.009419853799045086,
                    "z": 0.03407355025410652
                },
                "rotation": {
                    "x": 0.018311800435185432,
                    "y": -0.1403428614139557,
                    "z": 0.20703598856925964,
                    "w": 0.9680417776107788
                }
            },
            {
                "position": {
                    "x": -0.035054076462984085,
                    "y": -0.013691193424165249,
                    "z": 0.0778958648443222
                },
                "rotation": {
                    "x": -0.0492732934653759,
                    "y": -0.1622963398694992,
                    "z": 0.0986529216170311,
                    "w": 0.9805610179901123
                }
            },
            {
                "position": {
                    "x": -0.045130517333745956,
                    "y": -0.011706363409757614,
                    "z": 0.10684874653816223
                },
                "rotation": {
                    "x": 0.44840943813323975,
                    "y": -0.10068875551223755,
                    "z": 0.24488377571105957,
                    "w": 0.8537113070487976
                }
            },
            {
                "position": {
                    "x": -0.044161733239889145,
                    "y": -0.028258927166461945,
                    "z": 0.11858025938272476
                },
                "rotation": {
                    "x": 0.6715754270553589,
                    "y": 0.017967689782381058,
                    "z": 0.28297823667526245,
                    "w": 0.6845343708992004
                }
            },
            {
                "position": {
                    "x": -0.03552507981657982,
                    "y": -0.048166319727897644,
                    "z": 0.12193199247121811
                },
                "rotation": {
                    "x": 0.6715754270553589,
                    "y": 0.017967689782381058,
                    "z": 0.28297823667526245,
                    "w": 0.6845343708992004
                }
            }
        ],
        "right": [
            {
                "position": {
                    "x": -0.0008157475385814905,
                    "y": -0.0060463277623057365,
                    "z": 0.06582213193178177
                },
                "rotation": {
                    "x": 0.0,
                    "y": 0.0,
                    "z": 0.0,
                    "w": 1.0000001192092896
                }
            },
            {
                "position": {
                    "x": 0.0,
                    "y": 0.0,
                    "z": 0.0
                },
                "rotation": {
                    "x": 0.0,
                    "y": 0.0,
                    "z": 0.0,
                    "w": 1.0000001192092896
                }
            },
            {
                "position": {
                    "x": -0.02280975505709648,
                    "y": -0.023691797628998756,
                    "z": 0.037921808660030365
                },
                "rotation": {
                    "x": 0.1363598108291626,
                    "y": -0.36367732286453247,
                    "z": 0.7038857936859131,
                    "w": 0.5947183966636658
                }
            },
            {
                "position": {
                    "x": -0.03063262067735195,
                    "y": -0.04561089351773262,
                    "z": 0.06062518432736397
                },
                "rotation": {
                    "x": 0.3343012034893036,
                    "y": -0.0652560293674469,
                    "z": 0.7413091063499451,
                    "w": 0.5783127546310425
                }
            },
            {
                "position": {
                    "x": -0.0164339579641819,
                    "y": -0.06194685772061348,
                    "z": 0.08657728880643845
                },
                "rotation": {
                    "x": 0.508040726184845,
                    "y": 0.11138713359832764,
                    "z": 0.7558731436729431,
                    "w": 0.3976730406284332
                }
            },
            {
                "position": {
                    "x": 0.004017531406134367,
                    "y": -0.06794016808271408,
                    "z": 0.09890725463628769
                },
                "rotation": {
                    "x": 0.508040726184845,
                    "y": 0.11138713359832764,
                    "z": 0.7558731436729431,
                    "w": 0.3976730406284332
                }
            },
            {
                "position": {
                    "x": -0.016115013509988785,
                    "y": -0.013309195637702942,
                    "z": 0.038160160183906555
                },
                "rotation": {
                    "x": 0.0,
                    "y": 0.0,
                    "z": 0.0,
                    "w": 1.0000001192092896
                }
            },
            {
                "position": {
                    "x": -0.02355067804455757,
                    "y": -0.007316458038985729,
                    "z": 0.09599629044532776
                },
                "rotation": {
                    "x": 0.500271737575531,
                    "y": 0.02237323857843876,
                    "z": 0.036915190517902374,
                    "w": 0.8647919297218323
                }
            },
            {
                "position": {
                    "x": -0.02068217284977436,
                    "y": -0.04007088765501976,
                    "z": 0.11490131914615631
                },
                "rotation": {
                    "x": 0.9929195046424866,
                    "y": 0.038416095077991486,
                    "z": -0.02128087729215622,
                    "w": 0.1103735864162445
                }
            },
            {
                "position": {
                    "x": -0.021503165364265442,
                    "y": -0.04543758183717728,
                    "z": 0.09121178835630417
                },
                "rotation": {
                    "x": 0.8830991983413696,
                    "y": 0.037447959184646606,
                    "z": -0.02875325083732605,
                    "w": -0.46680524945259094
                }
            },
            {
                "position": {
                    "x": -0.023086141794919968,
                    "y": -0.0275957640260458,
                    "z": 0.07777970284223557
                },
                "rotation": {
                    "x": 0.8830991983413696,
                    "y": 0.037447959184646606,
                    "z": -0.02875325083732605,
                    "w": -0.46680524945259094
                }
            },
            {
                "position": {
                    "x": 9.440597204957157e-05,
                    "y": -0.009549479000270367,
                    "z": 0.03599763661623001
                },
                "rotation": {
                    "x": 0.0,
                    "y": 0.0,
                    "z": 0.0,
                    "w": 1.0000001192092896
                }
            },
            {
                "position": {
                    "x": -0.0017258949810639024,
                    "y": -0.002543172799050808,
                    "z": 0.09564662724733353
                },
                "rotation": {
                    "x": 0.5509809255599976,
                    "y": 0.037455566227436066,
                    "z": -0.029893606901168823,
                    "w": 0.8331409692764282
                }
            },
            {
                "position": {
                    "x": -0.0004608458839356899,
                    "y": -0.04205010458827019,
                    "z": 0.11238963156938553
                },
                "rotation": {
                    "x": 0.987777829170227,
                    "y": 0.004825599491596222,
                    "z": -0.06110662221908569,
                    "w": 0.14331114292144775
                }
            },
            {
                "position": {
                    "x": -0.0037485091015696526,
                    "y": -0.04986617714166641,
                    "z": 0.08617743104696274
                },
                "rotation": {
                    "x": 0.8931006789207458,
                    "y": 0.05613888055086136,
                    "z": -0.08968676626682281,
                    "w": -0.43723729252815247
                }
            },
            {
                "position": {
                    "x": -0.008646837435662746,
                    "y": -0.03126024827361107,
                    "z": 0.07022561132907867
                },
                "rotation": {
                    "x": 0.8931006789207458,
                    "y": 0.05613888055086136,
                    "z": -0.08968676626682281,
                    "w": -0.43723729252815247
                }
            },
            {
                "position": {
                    "x": 0.014992342330515385,
                    "y": -0.0060157799161970615,
                    "z": 0.034775517880916595
                },
                "rotation": {
                    "x": 0.0,
                    "y": 0.0,
                    "z": 0.0,
                    "w": 1.0000001192092896
                }
            },
            {
                "position": {
                    "x": 0.017465244978666306,
                    "y": -0.006529322359710932,
                    "z": 0.0886937752366066
                },
                "rotation": {
                    "x": 0.5717025995254517,
                    "y": 0.05605744197964668,
                    "z": -0.09395534545183182,
                    "w": 0.8131335973739624
                }
            },
            {
                "position": {
                    "x": 0.016830990090966225,
                    "y": -0.04319638013839722,
                    "z": 0.10195355117321014
                },
                "rotation": {
                    "x": 0.9814003109931946,
                    "y": -0.027490876615047455,
                    "z": -0.1509440839290619,
                    "w": 0.11538634449243546
                }
            },
            {
                "position": {
                    "x": 0.008789435029029846,
                    "y": -0.048994194716215134,
                    "z": 0.07729866355657578
                },
                "rotation": {
                    "x": 0.8770139813423157,
                    "y": -0.08024520426988602,
                    "z": -0.14025582373142242,
                    "w": -0.452477365732193
                }
            },
            {
                "position": {
                    "x": 0.004385378677397966,
                    "y": -0.03007253259420395,
                    "z": 0.06256809085607529
                },
                "rotation": {
                    "x": 0.8770139813423157,
                    "y": -0.08024520426988602,
                    "z": -0.14025582373142242,
                    "w": -0.452477365732193
                }
            },
            {
                "position": {
                    "x": 0.022998586297035217,
                    "y": -0.009419837035238743,
                    "z": 0.03407358378171921
                },
                "rotation": {
                    "x": 0.01831177808344364,
                    "y": 0.14034289121627808,
                    "z": -0.20703598856925964,
                    "w": 0.968041718006134
                }
            },
            {
                "position": {
                    "x": 0.03505407273769379,
                    "y": -0.013691186904907227,
                    "z": 0.0778958797454834
                },
                "rotation": {
                    "x": 0.5828532576560974,
                    "y": 0.011371053755283356,
                    "z": -0.17892038822174072,
                    "w": 0.7925530672073364
                }
            },
            {
                "position": {
                    "x": 0.02920047752559185,
                    "y": -0.0421983078122139,
                    "z": 0.08773574978113174
                },
                "rotation": {
                    "x": 0.9709392786026001,
                    "y": -0.06759098172187805,
                    "z": -0.20185518264770508,
                    "w": 0.10937559604644775
                }
            },
            {
                "position": {
                    "x": 0.020938536152243614,
                    "y": -0.045958083122968674,
                    "z": 0.06956556439399719
                },
                "rotation": {
                    "x": 0.8677322864532471,
                    "y": -0.17243458330631256,
                    "z": -0.17311780154705048,
                    "w": -0.4328250586986542
                }
            },
            {
                "position": {
                    "x": 0.016861291602253914,
                    "y": -0.028833512216806412,
                    "z": 0.05644096061587334
                },
                "rotation": {
                    "x": 0.8677322864532471,
                    "y": -0.17243458330631256,
                    "z": -0.17311780154705048,
                    "w": -0.4328250586986542
                }
            }
        ],
        "rootL": {
            "x": -0.17098355293273926,
            "y": 0.5841962695121765,
            "z": 0.2754554748535156
        },
        "rootR": {
            "x": 0.13633990287780762,
            "y": 0.9946377277374268,
            "z": 0.3437904119491577
        },
        "RighthandRotation": {
            "x": -0.7015060782432556,
            "y": -0.19795745611190796,
            "z": -0.11559569835662842,
            "w": 0.6747887134552002
        },
        "LefthandRotation": {
            "x": 0.12406362593173981,
            "y": -0.1314934492111206,
            "z": -0.273057758808136,
            "w": -0.9448583126068115
        },
        "headPos": {
            "x": -0.015180549584329128,
            "y": 1.148935317993164,
            "z": 0.12885746359825134
        },
        "headRot": {
            "x": -0.0314212441444397,
            "y": 0.03530103340744972,
            "z": 0.017719954252243042,
            "w": 0.9987255334854126
        }
    }
]