[
    {
        "left": [
            {
                "position": {
                    "x": 0.0028294026851654053,
                    "y": -0.004946637898683548,
                    "z": 0.06481987237930298
                },
                "rotation": {
                    "x": 0.0,
                    "y": 0.0,
                    "z": 0.0,
                    "w": 0.9999997615814209
                }
            },
            {
                "position": {
                    "x": 0.0,
                    "y": 0.0,
                    "z": 0.0
                },
                "rotation": {
                    "x": 0.0,
                    "y": 0.0,
                    "z": 0.0,
                    "w": 0.9999997615814209
                }
            },
            {
                "position": {
                    "x": 0.030864397063851357,
                    "y": -0.014894189313054085,
                    "z": 0.03391283005475998
                },
                "rotation": {
                    "x": -0.08891574293375015,
                    "y": 0.40305036306381226,
                    "z": -0.5548146963119507,
                    "w": 0.7223745584487915
                }
            },
            {
                "position": {
                    "x": 0.053004734218120575,
                    "y": -0.0252585019916296,
                    "z": 0.05534821376204491
                },
                "rotation": {
                    "x": 0.11287032067775726,
                    "y": 0.2144053727388382,
                    "z": -0.5767114162445068,
                    "w": 0.7801887392997742
                }
            },
            {
                "position": {
                    "x": 0.05991088226437569,
                    "y": -0.03956722840666771,
                    "z": 0.08517337590456009
                },
                "rotation": {
                    "x": 0.26952335238456726,
                    "y": 0.14057864248752594,
                    "z": -0.6596370935440063,
                    "w": 0.6873672604560852
                }
            },
            {
                "position": {
                    "x": 0.056868016719818115,
                    "y": -0.05269813910126686,
                    "z": 0.10577749460935593
                },
                "rotation": {
                    "x": 0.26952335238456726,
                    "y": 0.14057864248752594,
                    "z": -0.6596370935440063,
                    "w": 0.6873672604560852
                }
            },
            {
                "position": {
                    "x": 0.020142344757914543,
                    "y": -0.00891039241105318,
                    "z": 0.03615564480423927
                },
                "rotation": {
                    "x": 0.0,
                    "y": 0.0,
                    "z": 0.0,
                    "w": 0.9999997615814209
                }
            },
            {
                "position": {
                    "x": 0.023550676181912422,
                    "y": -0.007316476199775934,
                    "z": 0.09599623084068298
                },
                "rotation": {
                    "x": 0.16760064661502838,
                    "y": 0.08118291199207306,
                    "z": -0.04339635744690895,
                    "w": 0.9815475940704346
                }
            },
            {
                "position": {
                    "x": 0.029043450951576233,
                    "y": -0.020062359049916267,
                    "z": 0.13129281997680664
                },
                "rotation": {
                    "x": 0.3847240209579468,
                    "y": 0.063768170773983,
                    "z": -0.03477872908115387,
                    "w": 0.9201691746711731
                }
            },
            {
                "position": {
                    "x": 0.031245222315192223,
                    "y": -0.03737770766019821,
                    "z": 0.14820432662963867
                },
                "rotation": {
                    "x": 0.47590795159339905,
                    "y": 0.031107982620596886,
                    "z": -0.03484285995364189,
                    "w": 0.8782538175582886
                }
            },
            {
                "position": {
                    "x": 0.03152430057525635,
                    "y": -0.055552951991558075,
                    "z": 0.1612749546766281
                },
                "rotation": {
                    "x": 0.47590795159339905,
                    "y": 0.031107982620596886,
                    "z": -0.03484285995364189,
                    "w": 0.8782538175582886
                }
            },
            {
                "position": {
                    "x": 0.003932919353246689,
                    "y": -0.007350083906203508,
                    "z": 0.0339931882917881
                },
                "rotation": {
                    "x": 0.0,
                    "y": 0.0,
                    "z": 0.0,
                    "w": 0.9999997615814209
                }
            },
            {
                "position": {
                    "x": 0.0017259123269468546,
                    "y": -0.0025431467220187187,
                    "z": 0.09564658999443054
                },
                "rotation": {
                    "x": 0.2501097619533539,
                    "y": 0.03603839874267578,
                    "z": 8.942559361457825e-05,
                    "w": 0.9675464630126953
                }
            },
            {
                "position": {
                    "x": 0.004721447825431824,
                    "y": -0.023318901658058167,
                    "z": 0.1330915093421936
                },
                "rotation": {
                    "x": 0.44508543610572815,
                    "y": 0.030316008254885674,
                    "z": 0.0040836334228515625,
                    "w": 0.8949654698371887
                }
            },
            {
                "position": {
                    "x": 0.0063165333122015,
                    "y": -0.04526008293032646,
                    "z": 0.14967526495456696
                },
                "rotation": {
                    "x": 0.543739378452301,
                    "y": 0.010243996977806091,
                    "z": 0.05122808739542961,
                    "w": 0.837626576423645
                }
            },
            {
                "position": {
                    "x": 0.007743851747363806,
                    "y": -0.06754554063081741,
                    "z": 0.16089831292629242
                },
                "rotation": {
                    "x": 0.543739378452301,
                    "y": 0.010243996977806091,
                    "z": 0.05122808739542961,
                    "w": 0.837626576423645
                }
            },
            {
                "position": {
                    "x": -0.014992336742579937,
                    "y": -0.006015781778842211,
                    "z": 0.03477553278207779
                },
                "rotation": {
                    "x": 0.0,
                    "y": 0.0,
                    "z": 0.0,
                    "w": 0.9999997615814209
                }
            },
            {
                "position": {
                    "x": -0.01746523194015026,
                    "y": -0.006529306061565876,
                    "z": 0.08869379013776779
                },
                "rotation": {
                    "x": 0.11382827162742615,
                    "y": -0.030302375555038452,
                    "z": 0.05497037246823311,
                    "w": 0.9915154576301575
                }
            },
            {
                "position": {
                    "x": -0.019320515915751457,
                    "y": -0.015461595728993416,
                    "z": 0.126607745885849
                },
                "rotation": {
                    "x": 0.38164693117141724,
                    "y": -0.012034357525408268,
                    "z": 0.10071685910224915,
                    "w": 0.9187254905700684
                }
            },
            {
                "position": {
                    "x": -0.017865264788269997,
                    "y": -0.03416084498167038,
                    "z": 0.14543236792087555
                },
                "rotation": {
                    "x": 0.5561129450798035,
                    "y": 0.030449874699115753,
                    "z": 0.12522441148757935,
                    "w": 0.8210541605949402
                }
            },
            {
                "position": {
                    "x": -0.013786383904516697,
                    "y": -0.055688630789518356,
                    "z": 0.15612490475177765
                },
                "rotation": {
                    "x": 0.5561129450798035,
                    "y": 0.030449874699115753,
                    "z": 0.12522441148757935,
                    "w": 0.8210541605949402
                }
            },
            {
                "position": {
                    "x": -0.022998565807938576,
                    "y": -0.009419821202754974,
                    "z": 0.034073539078235626
                },
                "rotation": {
                    "x": 0.018311772495508194,
                    "y": -0.1403428167104721,
                    "z": 0.20703595876693726,
                    "w": 0.9680414795875549
                }
            },
            {
                "position": {
                    "x": -0.03505405783653259,
                    "y": -0.01369120180606842,
                    "z": 0.07789584249258041
                },
                "rotation": {
                    "x": -0.03919641673564911,
                    "y": -0.1256113350391388,
                    "z": 0.10593865066766739,
                    "w": 0.9856277704238892
                }
            },
            {
                "position": {
                    "x": -0.04291591793298721,
                    "y": -0.012135116383433342,
                    "z": 0.10755245387554169
                },
                "rotation": {
                    "x": 0.35943546891212463,
                    "y": -0.09088550508022308,
                    "z": 0.21862439811229706,
                    "w": 0.9026345014572144
                }
            },
            {
                "position": {
                    "x": -0.04305625706911087,
                    "y": -0.026121897622942924,
                    "z": 0.1222800463438034
                },
                "rotation": {
                    "x": 0.5648108720779419,
                    "y": 0.01063704863190651,
                    "z": 0.24983865022659302,
                    "w": 0.7864196300506592
                }
            },
            {
                "position": {
                    "x": -0.036750126630067825,
                    "y": -0.04509211331605911,
                    "z": 0.1313627064228058
                },
                "rotation": {
                    "x": 0.5648108720779419,
                    "y": 0.01063704863190651,
                    "z": 0.24983865022659302,
                    "w": 0.7864196300506592
                }
            }
        ],
        "right": [
            {
                "position": {
                    "x": -0.0011262517655268312,
                    "y": -0.005939789582043886,
                    "z": 0.06573613733053207
                },
                "rotation": {
                    "x": 0.0,
                    "y": 0.0,
                    "z": 0.0,
                    "w": 1.0
                }
            },
            {
                "position": {
                    "x": 0.0,
                    "y": 0.0,
                    "z": 0.0
                },
                "rotation": {
                    "x": 0.0,
                    "y": 0.0,
                    "z": 0.0,
                    "w": 1.0
                }
            },
            {
                "position": {
                    "x": -0.024051843211054802,
                    "y": -0.022839363664388657,
                    "z": 0.037577759474515915
                },
                "rotation": {
                    "x": 0.06030896306037903,
                    "y": -0.32446175813674927,
                    "z": 0.691949725151062,
                    "w": 0.6421006917953491
                }
            },
            {
                "position": {
                    "x": -0.03488555923104286,
                    "y": -0.0399564653635025,
                    "z": 0.06300856173038483
                },
                "rotation": {
                    "x": 0.3279755115509033,
                    "y": 0.019093118607997894,
                    "z": 0.714320957660675,
                    "w": 0.6179105043411255
                }
            },
            {
                "position": {
                    "x": -0.01825409010052681,
                    "y": -0.052731674164533615,
                    "z": 0.08950691670179367
                },
                "rotation": {
                    "x": 0.4615466594696045,
                    "y": 0.08788275718688965,
                    "z": 0.7303712964057922,
                    "w": 0.49579164385795593
                }
            },
            {
                "position": {
                    "x": -0.00024772569304332137,
                    "y": -0.060795459896326065,
                    "z": 0.10423631966114044
                },
                "rotation": {
                    "x": 0.4615466594696045,
                    "y": 0.08788275718688965,
                    "z": 0.7303712964057922,
                    "w": 0.49579164385795593
                }
            },
            {
                "position": {
                    "x": -0.016736028715968132,
                    "y": -0.012883000075817108,
                    "z": 0.037988122552633286
                },
                "rotation": {
                    "x": 0.0,
                    "y": 0.0,
                    "z": 0.0,
                    "w": 1.0
                }
            },
            {
                "position": {
                    "x": -0.023550672456622124,
                    "y": -0.0073164524510502815,
                    "z": 0.09599626809358597
                },
                "rotation": {
                    "x": 0.2750929594039917,
                    "y": -0.0840994268655777,
                    "z": 0.05723230540752411,
                    "w": 0.9560208320617676
                }
            },
            {
                "position": {
                    "x": -0.028455207124352455,
                    "y": -0.027630876749753952,
                    "z": 0.12764668464660645
                },
                "rotation": {
                    "x": 0.2945721447467804,
                    "y": -0.06943225115537643,
                    "z": 0.03583093732595444,
                    "w": 0.9524298906326294
                }
            },
            {
                "position": {
                    "x": -0.031156491488218307,
                    "y": -0.041389092803001404,
                    "z": 0.14749819040298462
                },
                "rotation": {
                    "x": 0.2524569630622864,
                    "y": -0.040670137852430344,
                    "z": 0.02515232563018799,
                    "w": 0.966425895690918
                }
            },
            {
                "position": {
                    "x": -0.03240709379315376,
                    "y": -0.051445893943309784,
                    "z": 0.1674620509147644
                },
                "rotation": {
                    "x": 0.2524569630622864,
                    "y": -0.040670137852430344,
                    "z": 0.02515232563018799,
                    "w": 0.966425895690918
                }
            },
            {
                "position": {
                    "x": -0.0005266242078505456,
                    "y": -0.009336396120488644,
                    "z": 0.03582565858960152
                },
                "rotation": {
                    "x": 0.0,
                    "y": 0.0,
                    "z": 0.0,
                    "w": 1.0
                }
            },
            {
                "position": {
                    "x": -0.0017258828738704324,
                    "y": -0.0025431823451071978,
                    "z": 0.09564662724733353
                },
                "rotation": {
                    "x": 0.40586286783218384,
                    "y": 0.04841462895274162,
                    "z": -0.026426643133163452,
                    "w": 0.9122681021690369
                }
            },
            {
                "position": {
                    "x": 0.0011451689060777426,
                    "y": -0.034440916031599045,
                    "z": 0.12423015385866165
                },
                "rotation": {
                    "x": 0.6204025745391846,
                    "y": 0.04662397503852844,
                    "z": -0.04851283133029938,
                    "w": 0.7813922166824341
                }
            },
            {
                "position": {
                    "x": 0.001494194963015616,
                    "y": -0.06127641722559929,
                    "z": 0.13045231997966766
                },
                "rotation": {
                    "x": 0.739398717880249,
                    "y": 0.06926928460597992,
                    "z": -0.1064014881849289,
                    "w": 0.6611887812614441
                }
            },
            {
                "position": {
                    "x": 0.00042808038415387273,
                    "y": -0.08619803190231323,
                    "z": 0.12889891862869263
                },
                "rotation": {
                    "x": 0.739398717880249,
                    "y": 0.06926928460597992,
                    "z": -0.1064014881849289,
                    "w": 0.6611887812614441
                }
            },
            {
                "position": {
                    "x": 0.014992324635386467,
                    "y": -0.006015761289745569,
                    "z": 0.03477555513381958
                },
                "rotation": {
                    "x": 0.0,
                    "y": 0.0,
                    "z": 0.0,
                    "w": 1.0
                }
            },
            {
                "position": {
                    "x": 0.017465269193053246,
                    "y": -0.006529341917484999,
                    "z": 0.08869379013776779
                },
                "rotation": {
                    "x": 0.6030089855194092,
                    "y": 0.06040772795677185,
                    "z": -0.10146163403987885,
                    "w": 0.7889467477798462
                }
            },
            {
                "position": {
                    "x": 0.01641051657497883,
                    "y": -0.044111497700214386,
                    "z": 0.09904579073190689
                },
                "rotation": {
                    "x": 0.9651045799255371,
                    "y": -0.009877310134470463,
                    "z": -0.16103777289390564,
                    "w": 0.20625869929790497
                }
            },
            {
                "position": {
                    "x": 0.00804227776825428,
                    "y": -0.05460645630955696,
                    "z": 0.07611165195703506
                },
                "rotation": {
                    "x": 0.9365516304969788,
                    "y": -0.06740197539329529,
                    "z": -0.16758394241333008,
                    "w": -0.30040669441223145
                }
            },
            {
                "position": {
                    "x": 0.0012674995232373476,
                    "y": -0.04167865961790085,
                    "z": 0.056582506746053696
                },
                "rotation": {
                    "x": 0.9365516304969788,
                    "y": -0.06740197539329529,
                    "z": -0.16758394241333008,
                    "w": -0.30040669441223145
                }
            },
            {
                "position": {
                    "x": 0.022998617962002754,
                    "y": -0.009419858455657959,
                    "z": 0.03407355025410652
                },
                "rotation": {
                    "x": 0.01831178367137909,
                    "y": 0.14034292101860046,
                    "z": -0.20703598856925964,
                    "w": 0.968041718006134
                }
            },
            {
                "position": {
                    "x": 0.03505411371588707,
                    "y": -0.01369120366871357,
                    "z": 0.07789584994316101
                },
                "rotation": {
                    "x": 0.6425356864929199,
                    "y": 0.025014281272888184,
                    "z": -0.2010151892900467,
                    "w": 0.7389962673187256
                }
            },
            {
                "position": {
                    "x": 0.028254196047782898,
                    "y": -0.04317420348525047,
                    "z": 0.08321184664964676
                },
                "rotation": {
                    "x": 0.9439853429794312,
                    "y": -0.02979946695268154,
                    "z": -0.23122365772724152,
                    "w": 0.23353779315948486
                }
            },
            {
                "position": {
                    "x": 0.019104644656181335,
                    "y": -0.05184977874159813,
                    "z": 0.06728792935609818
                },
                "rotation": {
                    "x": 0.9406368732452393,
                    "y": -0.1393861174583435,
                    "z": -0.23620760440826416,
                    "w": -0.19995060563087463
                }
            },
            {
                "position": {
                    "x": 0.009941820986568928,
                    "y": -0.04319015145301819,
                    "z": 0.04931060969829559
                },
                "rotation": {
                    "x": 0.9406368732452393,
                    "y": -0.1393861174583435,
                    "z": -0.23620760440826416,
                    "w": -0.19995060563087463
                }
            }
        ],
        "rootL": {
            "x": -0.1856377124786377,
            "y": 0.599572479724884,
            "z": 0.2802976965904236
        },
        "rootR": {
            "x": 0.0863027572631836,
            "y": 1.0590887069702148,
            "z": 0.4411908984184265
        },
        "RighthandRotation": {
            "x": 0.05450764298439026,
            "y": -0.45429274439811707,
            "z": -0.41645753383636475,
            "w": 0.7856272459030151
        },
        "LefthandRotation": {
            "x": 0.020707126706838608,
            "y": -0.1004548966884613,
            "z": -0.20488430559635162,
            "w": -0.9733972549438477
        },
        "headPos": {
            "x": -0.02441432699561119,
            "y": 1.1826035976409912,
            "z": 0.15546914935112
        },
        "headRot": {
            "x": -0.03982105851173401,
            "y": -0.0778452455997467,
            "z": 0.0029740629252046347,
            "w": 0.9961654543876648
        }
    },
    {
        "left": [
            {
                "position": {
                    "x": 0.002966220024973154,
                    "y": -0.004798183683305979,
                    "z": 0.06467165052890778
                },
                "rotation": {
                    "x": 0.0,
                    "y": 0.0,
                    "z": 0.0,
                    "w": 1.0000001192092896
                }
            },
            {
                "position": {
                    "x": 0.0,
                    "y": 0.0,
                    "z": 0.0
                },
                "rotation": {
                    "x": 0.0,
                    "y": 0.0,
                    "z": 0.0,
                    "w": 1.0000001192092896
                }
            },
            {
                "position": {
                    "x": 0.03141164779663086,
                    "y": -0.01370670460164547,
                    "z": 0.03331974148750305
                },
                "rotation": {
                    "x": -0.11644197255373001,
                    "y": 0.4000045359134674,
                    "z": -0.5324088335037231,
                    "w": 0.7368707656860352
                }
            },
            {
                "position": {
                    "x": 0.05460937321186066,
                    "y": -0.021975617855787277,
                    "z": 0.054546620696783066
                },
                "rotation": {
                    "x": 0.09070646017789841,
                    "y": 0.21921169757843018,
                    "z": -0.5518468618392944,
                    "w": 0.7994896769523621
                }
            },
            {
                "position": {
                    "x": 0.06307124346494675,
                    "y": -0.03505289927124977,
                    "z": 0.0845358595252037
                },
                "rotation": {
                    "x": 0.24970893561840057,
                    "y": 0.1496182680130005,
                    "z": -0.6386438608169556,
                    "w": 0.7123159170150757
                }
            },
            {
                "position": {
                    "x": 0.06138719245791435,
                    "y": -0.04787930101156235,
                    "z": 0.10548476874828339
                },
                "rotation": {
                    "x": 0.24970893561840057,
                    "y": 0.1496182680130005,
                    "z": -0.6386438608169556,
                    "w": 0.7123159170150757
                }
            },
            {
                "position": {
                    "x": 0.020415950566530228,
                    "y": -0.00831667147576809,
                    "z": 0.0358591228723526
                },
                "rotation": {
                    "x": 0.0,
                    "y": 0.0,
                    "z": 0.0,
                    "w": 1.0000001192092896
                }
            },
            {
                "position": {
                    "x": 0.023550691083073616,
                    "y": -0.0073164370842278,
                    "z": 0.09599625319242477
                },
                "rotation": {
                    "x": 0.20169521868228912,
                    "y": 0.05324186012148857,
                    "z": -0.043462228029966354,
                    "w": 0.9770340919494629
                }
            },
            {
                "position": {
                    "x": 0.026831602677702904,
                    "y": -0.022440116852521896,
                    "z": 0.13062269985675812
                },
                "rotation": {
                    "x": 0.4333159625530243,
                    "y": 0.03510148823261261,
                    "z": -0.029464665800333023,
                    "w": 0.9000762104988098
                }
            },
            {
                "position": {
                    "x": 0.02774672396481037,
                    "y": -0.04144807532429695,
                    "z": 0.1457398533821106
                },
                "rotation": {
                    "x": 0.5410485863685608,
                    "y": 0.002416391856968403,
                    "z": -0.02863989770412445,
                    "w": 0.8405001759529114
                }
            },
            {
                "position": {
                    "x": 0.02690141648054123,
                    "y": -0.06135404482483864,
                    "z": 0.15595242381095886
                },
                "rotation": {
                    "x": 0.5410485863685608,
                    "y": 0.002416391856968403,
                    "z": -0.02863989770412445,
                    "w": 0.8405001759529114
                }
            },
            {
                "position": {
                    "x": 0.004206530284136534,
                    "y": -0.007053205277770758,
                    "z": 0.033696651458740234
                },
                "rotation": {
                    "x": 0.0,
                    "y": 0.0,
                    "z": 0.0,
                    "w": 1.0000001192092896
                }
            },
            {
                "position": {
                    "x": 0.0017259035957977176,
                    "y": -0.002543156733736396,
                    "z": 0.09564661979675293
                },
                "rotation": {
                    "x": 0.2678065896034241,
                    "y": 0.027312083169817924,
                    "z": 0.001372314989566803,
                    "w": 0.9630845785140991
                }
            },
            {
                "position": {
                    "x": 0.004015753511339426,
                    "y": -0.024683423340320587,
                    "z": 0.1323520988225937
                },
                "rotation": {
                    "x": 0.457617849111557,
                    "y": 0.021808471530675888,
                    "z": 0.007137175649404526,
                    "w": 0.8888530135154724
                }
            },
            {
                "position": {
                    "x": 0.005263779312372208,
                    "y": -0.047086719423532486,
                    "z": 0.14833691716194153
                },
                "rotation": {
                    "x": 0.534066915512085,
                    "y": 0.0014163153246045113,
                    "z": 0.052930738776922226,
                    "w": 0.8437825441360474
                }
            },
            {
                "position": {
                    "x": 0.006328119430691004,
                    "y": -0.06912904977798462,
                    "z": 0.16006886959075928
                },
                "rotation": {
                    "x": 0.534066915512085,
                    "y": 0.0014163153246045113,
                    "z": 0.052930738776922226,
                    "w": 0.8437825441360474
                }
            },
            {
                "position": {
                    "x": -0.014992354437708855,
                    "y": -0.006015794817358255,
                    "z": 0.03477553650736809
                },
                "rotation": {
                    "x": 0.0,
                    "y": 0.0,
                    "z": 0.0,
                    "w": 1.0000001192092896
                }
            },
            {
                "position": {
                    "x": -0.017465243116021156,
                    "y": -0.006529286969453096,
                    "z": 0.08869380503892899
                },
                "rotation": {
                    "x": 0.11718465387821198,
                    "y": -0.03195911645889282,
                    "z": 0.05517508089542389,
                    "w": 0.991061270236969
                }
            },
            {
                "position": {
                    "x": -0.01943126879632473,
                    "y": -0.01572464592754841,
                    "z": 0.12653924524784088
                },
                "rotation": {
                    "x": 0.3793680965900421,
                    "y": -0.014239566400647163,
                    "z": 0.10117553919553757,
                    "w": 0.9195873737335205
                }
            },
            {
                "position": {
                    "x": -0.018087279051542282,
                    "y": -0.03434211388230324,
                    "z": 0.14545299112796783
                },
                "rotation": {
                    "x": 0.5377237200737,
                    "y": 0.026792220771312714,
                    "z": 0.12536543607711792,
                    "w": 0.8333182334899902
                }
            },
            {
                "position": {
                    "x": -0.014260398223996162,
                    "y": -0.05541318655014038,
                    "z": 0.15710531175136566
                },
                "rotation": {
                    "x": 0.5377237200737,
                    "y": 0.026792220771312714,
                    "z": 0.12536543607711792,
                    "w": 0.8333182334899902
                }
            },
            {
                "position": {
                    "x": -0.022998590022325516,
                    "y": -0.009419861249625683,
                    "z": 0.034073568880558014
                },
                "rotation": {
                    "x": 0.018311787396669388,
                    "y": -0.14034289121627808,
                    "z": 0.20703597366809845,
                    "w": 0.9680417776107788
                }
            },
            {
                "position": {
                    "x": -0.03505406901240349,
                    "y": -0.013691182248294353,
                    "z": 0.07789584994316101
                },
                "rotation": {
                    "x": -0.04389209672808647,
                    "y": -0.10749875009059906,
                    "z": 0.10767193138599396,
                    "w": 0.987382709980011
                }
            },
            {
                "position": {
                    "x": -0.04186590760946274,
                    "y": -0.011739580892026424,
                    "z": 0.10778789222240448
                },
                "rotation": {
                    "x": 0.3443157374858856,
                    "y": -0.0761956200003624,
                    "z": 0.21140559017658234,
                    "w": 0.9115641117095947
                }
            },
            {
                "position": {
                    "x": -0.041730523109436035,
                    "y": -0.025144049897789955,
                    "z": 0.12304749339818954
                },
                "rotation": {
                    "x": 0.5406427383422852,
                    "y": 0.02019471675157547,
                    "z": 0.2382010817527771,
                    "w": 0.8065718412399292
                }
            },
            {
                "position": {
                    "x": -0.03559237718582153,
                    "y": -0.043585155159235,
                    "z": 0.13326413929462433
                },
                "rotation": {
                    "x": 0.5406427383422852,
                    "y": 0.02019471675157547,
                    "z": 0.2382010817527771,
                    "w": 0.8065718412399292
                }
            }
        ],
        "right": [
            {
                "position": {
                    "x": -0.000793292245361954,
                    "y": -0.006053494289517403,
                    "z": 0.06582780182361603
                },
                "rotation": {
                    "x": 0.0,
                    "y": 0.0,
                    "z": 0.0,
                    "w": 1.0
                }
            },
            {
                "position": {
                    "x": 0.0,
                    "y": 0.0,
                    "z": 0.0
                },
                "rotation": {
                    "x": 0.0,
                    "y": 0.0,
                    "z": 0.0,
                    "w": 1.0
                }
            },
            {
                "position": {
                    "x": -0.022719889879226685,
                    "y": -0.02374921925365925,
                    "z": 0.037944335490465164
                },
                "rotation": {
                    "x": 0.1061336100101471,
                    "y": -0.33394286036491394,
                    "z": 0.7081734538078308,
                    "w": 0.6129503846168518
                }
            },
            {
                "position": {
                    "x": -0.03114270232617855,
                    "y": -0.04335736110806465,
                    "z": 0.06247326359152794
                },
                "rotation": {
                    "x": 0.34328949451446533,
                    "y": 0.002511456608772278,
                    "z": 0.7358221411705017,
                    "w": 0.5837053060531616
                }
            },
            {
                "position": {
                    "x": -0.013971313834190369,
                    "y": -0.056775376200675964,
                    "z": 0.08830104023218155
                },
                "rotation": {
                    "x": 0.4119674563407898,
                    "y": -0.021157145500183105,
                    "z": 0.7592258453369141,
                    "w": 0.5033999681472778
                }
            },
            {
                "position": {
                    "x": -1.831181361922063e-05,
                    "y": -0.06776970624923706,
                    "z": 0.10534945875406265
                },
                "rotation": {
                    "x": 0.4119674563407898,
                    "y": -0.021157145500183105,
                    "z": 0.7592258453369141,
                    "w": 0.5033999681472778
                }
            },
            {
                "position": {
                    "x": -0.01607006974518299,
                    "y": -0.013337907381355762,
                    "z": 0.03817141801118851
                },
                "rotation": {
                    "x": 0.0,
                    "y": 0.0,
                    "z": 0.0,
                    "w": 1.0
                }
            },
            {
                "position": {
                    "x": -0.02355068549513817,
                    "y": -0.007316445000469685,
                    "z": 0.09599623829126358
                },
                "rotation": {
                    "x": 0.32392239570617676,
                    "y": 0.022515207529067993,
                    "z": 0.03400924801826477,
                    "w": 0.9452041387557983
                }
            },
            {
                "position": {
                    "x": -0.021100763231515884,
                    "y": -0.030482998117804527,
                    "z": 0.12592600286006927
                },
                "rotation": {
                    "x": 0.339913547039032,
                    "y": 0.037878528237342834,
                    "z": 0.011265337467193604,
                    "w": 0.9396262168884277
                }
            },
            {
                "position": {
                    "x": -0.019184648990631104,
                    "y": -0.045986998826265335,
                    "z": 0.14454379677772522
                },
                "rotation": {
                    "x": 0.28038910031318665,
                    "y": 0.06793849170207977,
                    "z": 0.007598012685775757,
                    "w": 0.957449197769165
                }
            },
            {
                "position": {
                    "x": -0.015862928703427315,
                    "y": -0.05709186941385269,
                    "z": 0.16369861364364624
                },
                "rotation": {
                    "x": 0.28038910031318665,
                    "y": 0.06793849170207977,
                    "z": 0.007598012685775757,
                    "w": 0.957449197769165
                }
            },
            {
                "position": {
                    "x": 0.00013936632603872567,
                    "y": -0.009563849307596684,
                    "z": 0.036008939146995544
                },
                "rotation": {
                    "x": 0.0,
                    "y": 0.0,
                    "z": 0.0,
                    "w": 1.0
                }
            },
            {
                "position": {
                    "x": -0.0017259559826925397,
                    "y": -0.0025431641843169928,
                    "z": 0.09564663469791412
                },
                "rotation": {
                    "x": 0.3412095010280609,
                    "y": 0.046068742871284485,
                    "z": -0.02200058102607727,
                    "w": 0.9385998845100403
                }
            },
            {
                "position": {
                    "x": 0.0013419304741546512,
                    "y": -0.030125699937343597,
                    "z": 0.1283959597349167
                },
                "rotation": {
                    "x": 0.34350264072418213,
                    "y": 0.053901106119155884,
                    "z": -0.031226664781570435,
                    "w": 0.9370836019515991
                }
            },
            {
                "position": {
                    "x": 0.003533972892910242,
                    "y": -0.047954343259334564,
                    "z": 0.14928407967090607
                },
                "rotation": {
                    "x": 0.28098905086517334,
                    "y": 0.07167597115039825,
                    "z": -0.061513736844062805,
                    "w": 0.9550517797470093
                }
            },
            {
                "position": {
                    "x": 0.0065714046359062195,
                    "y": -0.0606483556330204,
                    "z": 0.17059774696826935
                },
                "rotation": {
                    "x": 0.28098905086517334,
                    "y": 0.07167597115039825,
                    "z": -0.061513736844062805,
                    "w": 0.9550517797470093
                }
            },
            {
                "position": {
                    "x": 0.014992316253483295,
                    "y": -0.006015782244503498,
                    "z": 0.034775543957948685
                },
                "rotation": {
                    "x": 0.0,
                    "y": 0.0,
                    "z": 0.0,
                    "w": 1.0
                }
            },
            {
                "position": {
                    "x": 0.017465194687247276,
                    "y": -0.006529311183840036,
                    "z": 0.08869380503892899
                },
                "rotation": {
                    "x": 0.5998825430870056,
                    "y": 0.04415863752365112,
                    "z": -0.08990752696990967,
                    "w": 0.7937932014465332
                }
            },
            {
                "position": {
                    "x": 0.015992704778909683,
                    "y": -0.04397750273346901,
                    "z": 0.09947160631418228
                },
                "rotation": {
                    "x": 0.9844983816146851,
                    "y": -0.02837425470352173,
                    "z": -0.1398233026266098,
                    "w": 0.10201729834079742
                }
            },
            {
                "position": {
                    "x": 0.008522870019078255,
                    "y": -0.0491044782102108,
                    "z": 0.07449038326740265
                },
                "rotation": {
                    "x": 0.920543909072876,
                    "y": -0.06635336577892303,
                    "z": -0.14223843812942505,
                    "w": -0.3577215373516083
                }
            },
            {
                "position": {
                    "x": 0.003192414063960314,
                    "y": -0.033811889588832855,
                    "z": 0.056265778839588165
                },
                "rotation": {
                    "x": 0.920543909072876,
                    "y": -0.06635336577892303,
                    "z": -0.14223843812942505,
                    "w": -0.3577215373516083
                }
            },
            {
                "position": {
                    "x": 0.022998569533228874,
                    "y": -0.009419845417141914,
                    "z": 0.03407355770468712
                },
                "rotation": {
                    "x": 0.018311768770217896,
                    "y": 0.1403428614139557,
                    "z": -0.20703597366809845,
                    "w": 0.9680416584014893
                }
            },
            {
                "position": {
                    "x": 0.035054102540016174,
                    "y": -0.013691182248294353,
                    "z": 0.07789583504199982
                },
                "rotation": {
                    "x": 0.67645263671875,
                    "y": 0.004672955721616745,
                    "z": -0.19354113936424255,
                    "w": 0.7105855941772461
                }
            },
            {
                "position": {
                    "x": 0.027214182540774345,
                    "y": -0.043279971927404404,
                    "z": 0.08050033450126648
                },
                "rotation": {
                    "x": 0.9673681855201721,
                    "y": -0.049828097224235535,
                    "z": -0.20871062576770782,
                    "w": 0.13474446535110474
                }
            },
            {
                "position": {
                    "x": 0.018739715218544006,
                    "y": -0.04815259948372841,
                    "z": 0.06269601732492447
                },
                "rotation": {
                    "x": 0.9283230304718018,
                    "y": -0.13820450007915497,
                    "z": -0.2132028341293335,
                    "w": -0.2714056372642517
                }
            },
            {
                "position": {
                    "x": 0.011039070785045624,
                    "y": -0.03676963970065117,
                    "z": 0.04557119309902191
                },
                "rotation": {
                    "x": 0.9283230304718018,
                    "y": -0.13820450007915497,
                    "z": -0.2132028341293335,
                    "w": -0.2714056372642517
                }
            }
        ],
        "rootL": {
            "x": -0.1904149055480957,
            "y": 0.5962616205215454,
            "z": 0.2798486351966858
        },
        "rootR": {
            "x": 0.05128622055053711,
            "y": 0.9970614910125732,
            "z": 0.3998788595199585
        },
        "RighthandRotation": {
            "x": 0.36359870433807373,
            "y": -0.5461582541465759,
            "z": -0.5870991349220276,
            "w": 0.47415369749069214
        },
        "LefthandRotation": {
            "x": 0.019802402704954147,
            "y": -0.1303635835647583,
            "z": -0.1982913613319397,
            "w": -0.9712331295013428
        },
        "headPos": {
            "x": -0.03692170977592468,
            "y": 1.182227611541748,
            "z": 0.1449485421180725
        },
        "headRot": {
            "x": -0.046109795570373535,
            "y": -0.137349933385849,
            "z": 0.0027561569586396217,
            "w": 0.9894449710845947
        }
    },
    {
        "left": [
            {
                "position": {
                    "x": 0.0029787402600049973,
                    "y": -0.004783182870596647,
                    "z": 0.06465655565261841
                },
                "rotation": {
                    "x": 0.0,
                    "y": 0.0,
                    "z": 0.0,
                    "w": 1.0000001192092896
                }
            },
            {
                "position": {
                    "x": 0.0,
                    "y": 0.0,
                    "z": 0.0
                },
                "rotation": {
                    "x": 0.0,
                    "y": 0.0,
                    "z": 0.0,
                    "w": 1.0000001192092896
                }
            },
            {
                "position": {
                    "x": 0.03146174177527428,
                    "y": -0.013586861081421375,
                    "z": 0.03325934335589409
                },
                "rotation": {
                    "x": -0.11876507103443146,
                    "y": 0.40023285150527954,
                    "z": -0.530251145362854,
                    "w": 0.7379314303398132
                }
            },
            {
                "position": {
                    "x": 0.054761771112680435,
                    "y": -0.021687977015972137,
                    "z": 0.05443883314728737
                },
                "rotation": {
                    "x": 0.083540178835392,
                    "y": 0.2238217145204544,
                    "z": -0.5477663278579712,
                    "w": 0.8017961978912354
                }
            },
            {
                "position": {
                    "x": 0.0637979656457901,
                    "y": -0.03450125828385353,
                    "z": 0.08437445014715195
                },
                "rotation": {
                    "x": 0.24220219254493713,
                    "y": 0.1548384577035904,
                    "z": -0.6359754800796509,
                    "w": 0.7161696553230286
                }
            },
            {
                "position": {
                    "x": 0.06259267032146454,
                    "y": -0.04723912104964256,
                    "z": 0.10541024059057236
                },
                "rotation": {
                    "x": 0.24220219254493713,
                    "y": 0.1548384577035904,
                    "z": -0.6359754800796509,
                    "w": 0.7161696553230286
                }
            },
            {
                "position": {
                    "x": 0.02044101618230343,
                    "y": -0.008256716653704643,
                    "z": 0.03582893684506416
                },
                "rotation": {
                    "x": 0.0,
                    "y": 0.0,
                    "z": 0.0,
                    "w": 1.0000001192092896
                }
            },
            {
                "position": {
                    "x": 0.023550676181912422,
                    "y": -0.007316482253372669,
                    "z": 0.09599625319242477
                },
                "rotation": {
                    "x": 0.21340006589889526,
                    "y": 0.044122304767370224,
                    "z": -0.04310721904039383,
                    "w": 0.9750157594680786
                }
            },
            {
                "position": {
                    "x": 0.02611614018678665,
                    "y": -0.02324368618428707,
                    "z": 0.13032153248786926
                },
                "rotation": {
                    "x": 0.4675559103488922,
                    "y": 0.025333624333143234,
                    "z": -0.027706217020750046,
                    "w": 0.8831662535667419
                }
            },
            {
                "position": {
                    "x": 0.026573996990919113,
                    "y": -0.04334918037056923,
                    "z": 0.14396804571151733
                },
                "rotation": {
                    "x": 0.5824598670005798,
                    "y": -0.0074053239077329636,
                    "z": -0.02690591663122177,
                    "w": 0.8123806715011597
                }
            },
            {
                "position": {
                    "x": 0.02534482441842556,
                    "y": -0.06416052579879761,
                    "z": 0.15213115513324738
                },
                "rotation": {
                    "x": 0.5824598670005798,
                    "y": -0.0074053239077329636,
                    "z": -0.02690591663122177,
                    "w": 0.8123806715011597
                }
            },
            {
                "position": {
                    "x": 0.0042315940372645855,
                    "y": -0.0070232548750936985,
                    "z": 0.0336664542555809
                },
                "rotation": {
                    "x": 0.0,
                    "y": 0.0,
                    "z": 0.0,
                    "w": 1.0000001192092896
                }
            },
            {
                "position": {
                    "x": 0.001725889858789742,
                    "y": -0.002543173497542739,
                    "z": 0.09564665704965591
                },
                "rotation": {
                    "x": 0.27540895342826843,
                    "y": 0.019960232079029083,
                    "z": 0.0028932150453329086,
                    "w": 0.9611157178878784
                }
            },
            {
                "position": {
                    "x": 0.003441337961703539,
                    "y": -0.025263765826821327,
                    "z": 0.13202741742134094
                },
                "rotation": {
                    "x": 0.4612051844596863,
                    "y": 0.014793150126934052,
                    "z": 0.010125219821929932,
                    "w": 0.8871126770973206
                }
            },
            {
                "position": {
                    "x": 0.004421702120453119,
                    "y": -0.04779880866408348,
                    "z": 0.14784477651119232
                },
                "rotation": {
                    "x": 0.5359588861465454,
                    "y": -0.005499276332557201,
                    "z": 0.056318238377571106,
                    "w": 0.8423459529876709
                }
            },
            {
                "position": {
                    "x": 0.005276251118630171,
                    "y": -0.06990646570920944,
                    "z": 0.15947046875953674
                },
                "rotation": {
                    "x": 0.5359588861465454,
                    "y": -0.005499276332557201,
                    "z": 0.056318238377571106,
                    "w": 0.8423459529876709
                }
            },
            {
                "position": {
                    "x": -0.014992338605225086,
                    "y": -0.006015763618052006,
                    "z": 0.03477555140852928
                },
                "rotation": {
                    "x": 0.0,
                    "y": 0.0,
                    "z": 0.0,
                    "w": 1.0000001192092896
                }
            },
            {
                "position": {
                    "x": -0.017465241253376007,
                    "y": -0.006529293023049831,
                    "z": 0.08869381994009018
                },
                "rotation": {
                    "x": 0.12992314994335175,
                    "y": -0.03214780613780022,
                    "z": 0.05554778128862381,
                    "w": 0.9894449710845947
                }
            },
            {
                "position": {
                    "x": -0.019383201375603676,
                    "y": -0.016694609075784683,
                    "z": 0.1262928545475006
                },
                "rotation": {
                    "x": 0.39072519540786743,
                    "y": -0.01487349160015583,
                    "z": 0.10158365964889526,
                    "w": 0.914764404296875
                }
            },
            {
                "position": {
                    "x": -0.017996840178966522,
                    "y": -0.0357707180082798,
                    "z": 0.1447407603263855
                },
                "rotation": {
                    "x": 0.547215461730957,
                    "y": 0.025873593986034393,
                    "z": 0.12612147629261017,
                    "w": 0.8270307183265686
                }
            },
            {
                "position": {
                    "x": -0.014137301594018936,
                    "y": -0.05709740146994591,
                    "z": 0.15590719878673553
                },
                "rotation": {
                    "x": 0.547215461730957,
                    "y": 0.025873593986034393,
                    "z": 0.12612147629261017,
                    "w": 0.8270307183265686
                }
            },
            {
                "position": {
                    "x": -0.02299858070909977,
                    "y": -0.009419831447303295,
                    "z": 0.03407356142997742
                },
                "rotation": {
                    "x": 0.018311787396669388,
                    "y": -0.1403428614139557,
                    "z": 0.20703604817390442,
                    "w": 0.968041718006134
                }
            },
            {
                "position": {
                    "x": -0.035054080188274384,
                    "y": -0.01369120180606842,
                    "z": 0.07789585739374161
                },
                "rotation": {
                    "x": -0.049546897411346436,
                    "y": -0.09775376319885254,
                    "z": 0.10820703208446503,
                    "w": 0.9880693554878235
                }
            },
            {
                "position": {
                    "x": -0.0413178913295269,
                    "y": -0.011333179660141468,
                    "z": 0.10787834227085114
                },
                "rotation": {
                    "x": 0.346596896648407,
                    "y": -0.06530062109231949,
                    "z": 0.2089972198009491,
                    "w": 0.9121003746986389
                }
            },
            {
                "position": {
                    "x": -0.04079480841755867,
                    "y": -0.02472975105047226,
                    "z": 0.1231364905834198
                },
                "rotation": {
                    "x": 0.5480335354804993,
                    "y": 0.031503111124038696,
                    "z": 0.23342087864875793,
                    "w": 0.8026095032691956
                }
            },
            {
                "position": {
                    "x": -0.03427201882004738,
                    "y": -0.04323878511786461,
                    "z": 0.13298530876636505
                },
                "rotation": {
                    "x": 0.5480335354804993,
                    "y": 0.031503111124038696,
                    "z": 0.23342087864875793,
                    "w": 0.8026095032691956
                }
            }
        ],
        "right": [
            {
                "position": {
                    "x": -0.0010982678504660726,
                    "y": -0.005949956364929676,
                    "z": 0.06574453413486481
                },
                "rotation": {
                    "x": 0.0,
                    "y": 0.0,
                    "z": 0.0,
                    "w": 1.0000001192092896
                }
            },
            {
                "position": {
                    "x": 0.0,
                    "y": 0.0,
                    "z": 0.0
                },
                "rotation": {
                    "x": 0.0,
                    "y": 0.0,
                    "z": 0.0,
                    "w": 1.0000001192092896
                }
            },
            {
                "position": {
                    "x": -0.023939840495586395,
                    "y": -0.022920899093151093,
                    "z": 0.037611350417137146
                },
                "rotation": {
                    "x": 0.08523835241794586,
                    "y": -0.3455965518951416,
                    "z": 0.6928457021713257,
                    "w": 0.6271066665649414
                }
            },
            {
                "position": {
                    "x": -0.03419237211346626,
                    "y": -0.041966911405324936,
                    "z": 0.06188531965017319
                },
                "rotation": {
                    "x": 0.3089299201965332,
                    "y": -0.04100479185581207,
                    "z": 0.7221148610115051,
                    "w": 0.6176014542579651
                }
            },
            {
                "position": {
                    "x": -0.020826639607548714,
                    "y": -0.05686327815055847,
                    "z": 0.08911455422639847
                },
                "rotation": {
                    "x": 0.40127992630004883,
                    "y": -0.025858119130134583,
                    "z": 0.7524951696395874,
                    "w": 0.5215910077095032
                }
            },
            {
                "position": {
                    "x": -0.007556258235126734,
                    "y": -0.06806865334510803,
                    "z": 0.10656576603651047
                },
                "rotation": {
                    "x": 0.40127992630004883,
                    "y": -0.025858119130134583,
                    "z": 0.7524951696395874,
                    "w": 0.5215910077095032
                }
            },
            {
                "position": {
                    "x": -0.016680054366588593,
                    "y": -0.012923759408295155,
                    "z": 0.03800491988658905
                },
                "rotation": {
                    "x": 0.0,
                    "y": 0.0,
                    "z": 0.0,
                    "w": 1.0000001192092896
                }
            },
            {
                "position": {
                    "x": -0.023550694808363914,
                    "y": -0.007316447328776121,
                    "z": 0.09599627554416656
                },
                "rotation": {
                    "x": 0.12544989585876465,
                    "y": -0.10437259078025818,
                    "z": 0.039922166615724564,
                    "w": 0.9857866764068604
                }
            },
            {
                "position": {
                    "x": -0.030975403264164925,
                    "y": -0.017013199627399445,
                    "z": 0.13190345466136932
                },
                "rotation": {
                    "x": 0.18663351237773895,
                    "y": -0.09292437881231308,
                    "z": 0.02105790749192238,
                    "w": 0.9777984619140625
                }
            },
            {
                "position": {
                    "x": -0.03520086780190468,
                    "y": -0.02597867324948311,
                    "z": 0.15409435331821442
                },
                "rotation": {
                    "x": 0.1616649478673935,
                    "y": -0.06448838859796524,
                    "z": 0.00757410004734993,
                    "w": 0.9847075343132019
                }
            },
            {
                "position": {
                    "x": -0.037729911506175995,
                    "y": -0.03215112164616585,
                    "z": 0.1754663586616516
                },
                "rotation": {
                    "x": 0.1616649478673935,
                    "y": -0.06448838859796524,
                    "z": 0.00757410004734993,
                    "w": 0.9847075343132019
                }
            },
            {
                "position": {
                    "x": -0.000470620027044788,
                    "y": -0.009356790222227573,
                    "z": 0.03584242984652519
                },
                "rotation": {
                    "x": 0.0,
                    "y": 0.0,
                    "z": 0.0,
                    "w": 1.0000001192092896
                }
            },
            {
                "position": {
                    "x": -0.0017259070882573724,
                    "y": -0.0025431339163333178,
                    "z": 0.09564665704965591
                },
                "rotation": {
                    "x": 0.4420834183692932,
                    "y": 0.039225202053785324,
                    "z": -0.024619210511446,
                    "w": 0.8957778811454773
                }
            },
            {
                "position": {
                    "x": 0.0003563272475730628,
                    "y": -0.03662499040365219,
                    "z": 0.12166241556406021
                },
                "rotation": {
                    "x": 0.8241585493087769,
                    "y": 0.026279564946889877,
                    "z": -0.05306082218885422,
                    "w": 0.563256025314331
                }
            },
            {
                "position": {
                    "x": -0.0012375805526971817,
                    "y": -0.062279537320137024,
                    "z": 0.1117485761642456
                },
                "rotation": {
                    "x": 0.9556402564048767,
                    "y": 0.06018040329217911,
                    "z": -0.11040098965167999,
                    "w": 0.26635003089904785
                }
            },
            {
                "position": {
                    "x": -0.005208444315940142,
                    "y": -0.0762704461812973,
                    "z": 0.09142319113016129
                },
                "rotation": {
                    "x": 0.9556402564048767,
                    "y": 0.06018040329217911,
                    "z": -0.11040098965167999,
                    "w": 0.26635003089904785
                }
            },
            {
                "position": {
                    "x": 0.014992338605225086,
                    "y": -0.006015772465616465,
                    "z": 0.034775540232658386
                },
                "rotation": {
                    "x": 0.0,
                    "y": 0.0,
                    "z": 0.0,
                    "w": 1.0000001192092896
                }
            },
            {
                "position": {
                    "x": 0.017465263605117798,
                    "y": -0.006529357749968767,
                    "z": 0.08869380503892899
                },
                "rotation": {
                    "x": 0.5500337481498718,
                    "y": 0.06294681131839752,
                    "z": -0.0951777845621109,
                    "w": 0.8273102045059204
                }
            },
            {
                "position": {
                    "x": 0.017443839460611343,
                    "y": -0.042486850172281265,
                    "z": 0.10378532856702805
                },
                "rotation": {
                    "x": 0.9217804074287415,
                    "y": 0.00544237345457077,
                    "z": -0.15792101621627808,
                    "w": 0.35405173897743225
                }
            },
            {
                "position": {
                    "x": 0.009809781797230244,
                    "y": -0.05987739562988281,
                    "z": 0.08519948273897171
                },
                "rotation": {
                    "x": 0.9814600348472595,
                    "y": -0.046176426112651825,
                    "z": -0.1818581223487854,
                    "w": -0.039140716195106506
                }
            },
            {
                "position": {
                    "x": 0.0012850228231400251,
                    "y": -0.0592159628868103,
                    "z": 0.06236734613776207
                },
                "rotation": {
                    "x": 0.9814600348472595,
                    "y": -0.046176426112651825,
                    "z": -0.1818581223487854,
                    "w": -0.039140716195106506
                }
            },
            {
                "position": {
                    "x": 0.02299858070909977,
                    "y": -0.009419836103916168,
                    "z": 0.03407357260584831
                },
                "rotation": {
                    "x": 0.018311789259314537,
                    "y": 0.14034287631511688,
                    "z": -0.20703598856925964,
                    "w": 0.9680417776107788
                }
            },
            {
                "position": {
                    "x": 0.03505408391356468,
                    "y": -0.01369118969887495,
                    "z": 0.0778958722949028
                },
                "rotation": {
                    "x": 0.609199047088623,
                    "y": 0.054656289517879486,
                    "z": -0.21300584077835083,
                    "w": 0.7619173526763916
                }
            },
            {
                "position": {
                    "x": 0.029639942571520805,
                    "y": -0.04292479529976845,
                    "z": 0.0856306403875351
                },
                "rotation": {
                    "x": 0.9354370832443237,
                    "y": -0.02161167375743389,
                    "z": -0.2597826421260834,
                    "w": 0.23875513672828674
                }
            },
            {
                "position": {
                    "x": 0.019558606669306755,
                    "y": -0.051769472658634186,
                    "z": 0.07037637382745743
                },
                "rotation": {
                    "x": 0.943343460559845,
                    "y": -0.13102485239505768,
                    "z": -0.27378910779953003,
                    "w": -0.13407281041145325
                }
            },
            {
                "position": {
                    "x": 0.008413748815655708,
                    "y": -0.04573903605341911,
                    "z": 0.052444394677877426
                },
                "rotation": {
                    "x": 0.943343460559845,
                    "y": -0.13102485239505768,
                    "z": -0.27378910779953003,
                    "w": -0.13407281041145325
                }
            }
        ],
        "rootL": {
            "x": -0.18925786018371582,
            "y": 0.5912559032440186,
            "z": 0.2818871736526489
        },
        "rootR": {
            "x": 0.15363240242004395,
            "y": 1.0681109428405762,
            "z": 0.4295575022697449
        },
        "RighthandRotation": {
            "x": -0.3103083372116089,
            "y": -0.2488023042678833,
            "z": -0.1602344512939453,
            "w": 0.9033998250961304
        },
        "LefthandRotation": {
            "x": 0.039115358144044876,
            "y": -0.1323874592781067,
            "z": -0.19742564857006073,
            "w": -0.9705497622489929
        },
        "headPos": {
            "x": -0.022771988064050674,
            "y": 1.1791881322860718,
            "z": 0.15814308822155
        },
        "headRot": {
            "x": -0.024541186168789864,
            "y": -0.04287976026535034,
            "z": 0.01332511380314827,
            "w": 0.9986899495124817
        }
    }
]