[
    {
        "left": [
            {
                "position": {
                    "x": 0.0027054750826209784,
                    "y": -0.005062759853899479,
                    "z": 0.06493430584669113
                },
                "rotation": {
                    "x": 0.0,
                    "y": 0.0,
                    "z": 0.0,
                    "w": 0.9999999403953552
                }
            },
            {
                "position": {
                    "x": 0.0,
                    "y": 0.0,
                    "z": 0.0
                },
                "rotation": {
                    "x": 0.0,
                    "y": 0.0,
                    "z": 0.0,
                    "w": 0.9999999403953552
                }
            },
            {
                "position": {
                    "x": 0.030368631705641747,
                    "y": -0.015823407098650932,
                    "z": 0.03437041491270065
                },
                "rotation": {
                    "x": -0.0873180478811264,
                    "y": 0.3772426247596741,
                    "z": -0.5664430856704712,
                    "w": 0.7274653315544128
                }
            },
            {
                "position": {
                    "x": 0.05142994970083237,
                    "y": -0.025588031858205795,
                    "z": 0.05713358148932457
                },
                "rotation": {
                    "x": 0.04708222299814224,
                    "y": 0.23425456881523132,
                    "z": -0.5582008361816406,
                    "w": 0.7945563197135925
                }
            },
            {
                "position": {
                    "x": 0.06223341450095177,
                    "y": -0.03695402294397354,
                    "z": 0.08706805109977722
                },
                "rotation": {
                    "x": 0.14840452373027802,
                    "y": 0.2105402946472168,
                    "z": -0.6396119594573975,
                    "w": 0.7242550253868103
                }
            },
            {
                "position": {
                    "x": 0.06601769477128983,
                    "y": -0.04814254492521286,
                    "z": 0.10867146402597427
                },
                "rotation": {
                    "x": 0.14840452373027802,
                    "y": 0.2105402946472168,
                    "z": -0.6396119594573975,
                    "w": 0.7242550253868103
                }
            },
            {
                "position": {
                    "x": 0.01989445835351944,
                    "y": -0.009374982677400112,
                    "z": 0.0363844633102417
                },
                "rotation": {
                    "x": 0.0,
                    "y": 0.0,
                    "z": 0.0,
                    "w": 0.9999999403953552
                }
            },
            {
                "position": {
                    "x": 0.023550696671009064,
                    "y": -0.0073164403438568115,
                    "z": 0.09599623084068298
                },
                "rotation": {
                    "x": 0.2076401561498642,
                    "y": 0.08199255168437958,
                    "z": -0.04831591248512268,
                    "w": 0.9735647439956665
                }
            },
            {
                "position": {
                    "x": 0.02884477935731411,
                    "y": -0.022951073944568634,
                    "z": 0.1301431506872177
                },
                "rotation": {
                    "x": 0.5533238649368286,
                    "y": 0.05579719692468643,
                    "z": -0.0492384098470211,
                    "w": 0.8296354413032532
                }
            },
            {
                "position": {
                    "x": 0.029770607128739357,
                    "y": -0.04539810121059418,
                    "z": 0.139413520693779
                },
                "rotation": {
                    "x": 0.7068876624107361,
                    "y": 0.016957657411694527,
                    "z": -0.05745219066739082,
                    "w": 0.704784631729126
                }
            },
            {
                "position": {
                    "x": 0.02830277569591999,
                    "y": -0.06771399825811386,
                    "z": 0.14046497642993927
                },
                "rotation": {
                    "x": 0.7068876624107361,
                    "y": 0.016957657411694527,
                    "z": -0.05745219066739082,
                    "w": 0.704784631729126
                }
            },
            {
                "position": {
                    "x": 0.003685026429593563,
                    "y": -0.007582394871860743,
                    "z": 0.034221988171339035
                },
                "rotation": {
                    "x": 0.0,
                    "y": 0.0,
                    "z": 0.0,
                    "w": 0.9999999403953552
                }
            },
            {
                "position": {
                    "x": 0.0017258984735235572,
                    "y": -0.0025431751273572445,
                    "z": 0.09564661234617233
                },
                "rotation": {
                    "x": 0.1309744268655777,
                    "y": -0.0072623188607394695,
                    "z": 0.008900720626115799,
                    "w": 0.9913192391395569
                }
            },
            {
                "position": {
                    "x": 0.0012079061707481742,
                    "y": -0.013695778325200081,
                    "z": 0.13709628582000732
                },
                "rotation": {
                    "x": 0.5940709114074707,
                    "y": -0.002134392037987709,
                    "z": 0.024355314671993256,
                    "w": 0.8040411472320557
                }
            },
            {
                "position": {
                    "x": 0.0019105742685496807,
                    "y": -0.04001714289188385,
                    "z": 0.14520004391670227
                },
                "rotation": {
                    "x": 0.8178566694259644,
                    "y": -0.026575716212391853,
                    "z": 0.0900920182466507,
                    "w": 0.5677039623260498
                }
            },
            {
                "position": {
                    "x": 0.0043672556057572365,
                    "y": -0.06373990327119827,
                    "z": 0.1377280056476593
                },
                "rotation": {
                    "x": 0.8178566694259644,
                    "y": -0.026575716212391853,
                    "z": 0.0900920182466507,
                    "w": 0.5677039623260498
                }
            },
            {
                "position": {
                    "x": -0.01499231904745102,
                    "y": -0.006015764083713293,
                    "z": 0.03477553278207779
                },
                "rotation": {
                    "x": 0.0,
                    "y": 0.0,
                    "z": 0.0,
                    "w": 0.9999999403953552
                }
            },
            {
                "position": {
                    "x": -0.017465244978666306,
                    "y": -0.006529325153678656,
                    "z": 0.08869380503892899
                },
                "rotation": {
                    "x": 0.031238680705428123,
                    "y": -0.0671791210770607,
                    "z": 0.05240870639681816,
                    "w": 0.995873749256134
                }
            },
            {
                "position": {
                    "x": -0.022555386647582054,
                    "y": -0.009230239316821098,
                    "z": 0.12726181745529175
                },
                "rotation": {
                    "x": 0.558379054069519,
                    "y": -0.01421566866338253,
                    "z": 0.12238283455371857,
                    "w": 0.8203861117362976
                }
            },
            {
                "position": {
                    "x": -0.0195433609187603,
                    "y": -0.033668529242277145,
                    "z": 0.137253999710083
                },
                "rotation": {
                    "x": 0.813829779624939,
                    "y": 0.043037090450525284,
                    "z": 0.15282270312309265,
                    "w": 0.5589941740036011
                }
            },
            {
                "position": {
                    "x": -0.012728959321975708,
                    "y": -0.05614102631807327,
                    "z": 0.1306993067264557
                },
                "rotation": {
                    "x": 0.813829779624939,
                    "y": 0.043037090450525284,
                    "z": 0.15282270312309265,
                    "w": 0.5589941740036011
                }
            },
            {
                "position": {
                    "x": -0.022998590022325516,
                    "y": -0.009419861249625683,
                    "z": 0.03407356142997742
                },
                "rotation": {
                    "x": 0.018311813473701477,
                    "y": -0.1403428316116333,
                    "z": 0.20703603327274323,
                    "w": 0.9680415987968445
                }
            },
            {
                "position": {
                    "x": -0.03505407273769379,
                    "y": -0.013691198080778122,
                    "z": 0.07789584249258041
                },
                "rotation": {
                    "x": -0.030397726222872734,
                    "y": -0.13577517867088318,
                    "z": 0.10604583472013474,
                    "w": 0.9845787286758423
                }
            },
            {
                "position": {
                    "x": -0.04346563294529915,
                    "y": -0.012737002223730087,
                    "z": 0.10742684453725815
                },
                "rotation": {
                    "x": 0.4846152663230896,
                    "y": -0.0716690719127655,
                    "z": 0.23974792659282684,
                    "w": 0.8381720185279846
                }
            },
            {
                "position": {
                    "x": -0.04118608310818672,
                    "y": -0.0299355611205101,
                    "z": 0.11798924952745438
                },
                "rotation": {
                    "x": 0.7691929340362549,
                    "y": 0.06916602700948715,
                    "z": 0.2680540084838867,
                    "w": 0.5759385228157043
                }
            },
            {
                "position": {
                    "x": -0.030436759814620018,
                    "y": -0.048841603100299835,
                    "z": 0.11496530473232269
                },
                "rotation": {
                    "x": 0.7691929340362549,
                    "y": 0.06916602700948715,
                    "z": 0.2680540084838867,
                    "w": 0.5759385228157043
                }
            }
        ],
        "right": [
            {
                "position": {
                    "x": -0.0015721494564786553,
                    "y": -0.0057595353573560715,
                    "z": 0.06558305025100708
                },
                "rotation": {
                    "x": 0.0,
                    "y": 0.0,
                    "z": 0.0,
                    "w": 0.9999999403953552
                }
            },
            {
                "position": {
                    "x": 0.0,
                    "y": 0.0,
                    "z": 0.0
                },
                "rotation": {
                    "x": 0.0,
                    "y": 0.0,
                    "z": 0.0,
                    "w": 0.9999999403953552
                }
            },
            {
                "position": {
                    "x": -0.025835322216153145,
                    "y": -0.0213975477963686,
                    "z": 0.03696538507938385
                },
                "rotation": {
                    "x": 0.04471737891435623,
                    "y": -0.35872024297714233,
                    "z": 0.6658324599266052,
                    "w": 0.6526769399642944
                }
            },
            {
                "position": {
                    "x": -0.03912362828850746,
                    "y": -0.038826655596494675,
                    "z": 0.06098072603344917
                },
                "rotation": {
                    "x": 0.11167950928211212,
                    "y": -0.2323715090751648,
                    "z": 0.6488392353057861,
                    "w": 0.7159181237220764
                }
            },
            {
                "position": {
                    "x": -0.045469772070646286,
                    "y": -0.054420486092567444,
                    "z": 0.09028143435716629
                },
                "rotation": {
                    "x": 0.09448354691267014,
                    "y": -0.3217279016971588,
                    "z": 0.6840879321098328,
                    "w": 0.6477559208869934
                }
            },
            {
                "position": {
                    "x": -0.05360880494117737,
                    "y": -0.06765411794185638,
                    "z": 0.10938215255737305
                },
                "rotation": {
                    "x": 0.09448354691267014,
                    "y": -0.3217279016971588,
                    "z": 0.6840879321098328,
                    "w": 0.6477559208869934
                }
            },
            {
                "position": {
                    "x": -0.01762777380645275,
                    "y": -0.012162084691226482,
                    "z": 0.03768191114068031
                },
                "rotation": {
                    "x": 0.0,
                    "y": 0.0,
                    "z": 0.0,
                    "w": 0.9999999403953552
                }
            },
            {
                "position": {
                    "x": -0.02355065383017063,
                    "y": -0.00731648551300168,
                    "z": 0.09599621593952179
                },
                "rotation": {
                    "x": 0.2061544954776764,
                    "y": -0.05097310245037079,
                    "z": 0.04353257268667221,
                    "w": 0.9762207269668579
                }
            },
            {
                "position": {
                    "x": -0.026644550263881683,
                    "y": -0.022750692442059517,
                    "z": 0.1305026262998581
                },
                "rotation": {
                    "x": 0.2749345004558563,
                    "y": -0.037149883806705475,
                    "z": 0.022569766268134117,
                    "w": 0.9604797959327698
                }
            },
            {
                "position": {
                    "x": -0.02807733602821827,
                    "y": -0.03562711551785469,
                    "z": 0.15106502175331116
                },
                "rotation": {
                    "x": 0.2591778337955475,
                    "y": -0.007737211883068085,
                    "z": 0.013458849862217903,
                    "w": 0.9657049179077148
                }
            },
            {
                "position": {
                    "x": -0.0279907938092947,
                    "y": -0.04593291133642197,
                    "z": 0.17094071209430695
                },
                "rotation": {
                    "x": 0.2591778337955475,
                    "y": -0.007737211883068085,
                    "z": 0.013458849862217903,
                    "w": 0.9657049179077148
                }
            },
            {
                "position": {
                    "x": -0.0014183709863573313,
                    "y": -0.0089759211987257,
                    "z": 0.03551948443055153
                },
                "rotation": {
                    "x": 0.0,
                    "y": 0.0,
                    "z": 0.0,
                    "w": 0.9999999403953552
                }
            },
            {
                "position": {
                    "x": -0.0017259209416806698,
                    "y": -0.0025431460235267878,
                    "z": 0.09564661234617233
                },
                "rotation": {
                    "x": 0.5633417963981628,
                    "y": 0.06765903532505035,
                    "z": -0.0495283380150795,
                    "w": 0.8219581842422485
                }
            },
            {
                "position": {
                    "x": 0.000653203809633851,
                    "y": -0.04258496314287186,
                    "z": 0.11093448847532272
                },
                "rotation": {
                    "x": 0.977019190788269,
                    "y": 0.01654604822397232,
                    "z": -0.0957527756690979,
                    "w": 0.1897137612104416
                }
            },
            {
                "position": {
                    "x": -0.0043284776620566845,
                    "y": -0.05288510024547577,
                    "z": 0.08587321639060974
                },
                "rotation": {
                    "x": 0.9076758623123169,
                    "y": 0.044384345412254333,
                    "z": -0.12876613438129425,
                    "w": -0.396955668926239
                }
            },
            {
                "position": {
                    "x": -0.010771313682198524,
                    "y": -0.03589834272861481,
                    "z": 0.06870996952056885
                },
                "rotation": {
                    "x": 0.9076758623123169,
                    "y": 0.044384345412254333,
                    "z": -0.12876613438129425,
                    "w": -0.396955668926239
                }
            },
            {
                "position": {
                    "x": 0.01499235536903143,
                    "y": -0.0060158078558743,
                    "z": 0.034775495529174805
                },
                "rotation": {
                    "x": 0.0,
                    "y": 0.0,
                    "z": 0.0,
                    "w": 0.9999999403953552
                }
            },
            {
                "position": {
                    "x": 0.01746523194015026,
                    "y": -0.006529295351356268,
                    "z": 0.08869384229183197
                },
                "rotation": {
                    "x": 0.6452564001083374,
                    "y": 0.04778188467025757,
                    "z": -0.09906300902366638,
                    "w": 0.7560075521469116
                }
            },
            {
                "position": {
                    "x": 0.015297256410121918,
                    "y": -0.04494455084204674,
                    "z": 0.09503928571939468
                },
                "rotation": {
                    "x": 0.9740437269210815,
                    "y": -0.013579302467405796,
                    "z": -0.1506420373916626,
                    "w": 0.16840845346450806
                }
            },
            {
                "position": {
                    "x": 0.0073773558251559734,
                    "y": -0.05355384945869446,
                    "z": 0.0711793303489685
                },
                "rotation": {
                    "x": 0.8949204683303833,
                    "y": -0.07112745195627213,
                    "z": -0.14784905314445496,
                    "w": -0.41496872901916504
                }
            },
            {
                "position": {
                    "x": 0.0022179794032126665,
                    "y": -0.03601375222206116,
                    "z": 0.055050499737262726
                },
                "rotation": {
                    "x": 0.8949204683303833,
                    "y": -0.07112745195627213,
                    "z": -0.14784905314445496,
                    "w": -0.41496872901916504
                }
            },
            {
                "position": {
                    "x": 0.022998563945293427,
                    "y": -0.009419829584658146,
                    "z": 0.03407358005642891
                },
                "rotation": {
                    "x": 0.018311820924282074,
                    "y": 0.1403428614139557,
                    "z": -0.20703594386577606,
                    "w": 0.9680416584014893
                }
            },
            {
                "position": {
                    "x": 0.035054031759500504,
                    "y": -0.01369116548448801,
                    "z": 0.0778958797454834
                },
                "rotation": {
                    "x": 0.6651538610458374,
                    "y": -0.005290411412715912,
                    "z": -0.1830102503299713,
                    "w": 0.7239127159118652
                }
            },
            {
                "position": {
                    "x": 0.027339570224285126,
                    "y": -0.0432162769138813,
                    "z": 0.08143133670091629
                },
                "rotation": {
                    "x": 0.9677299857139587,
                    "y": -0.05259222537279129,
                    "z": -0.19543476402759552,
                    "w": 0.15012715756893158
                }
            },
            {
                "position": {
                    "x": 0.019335903227329254,
                    "y": -0.04870050773024559,
                    "z": 0.06358708441257477
                },
                "rotation": {
                    "x": 0.8917024731636047,
                    "y": -0.15644758939743042,
                    "z": -0.17757821083068848,
                    "w": -0.38581976294517517
                }
            },
            {
                "position": {
                    "x": 0.014314938336610794,
                    "y": -0.03315775468945503,
                    "z": 0.04891253635287285
                },
                "rotation": {
                    "x": 0.8917024731636047,
                    "y": -0.15644758939743042,
                    "z": -0.17757821083068848,
                    "w": -0.38581976294517517
                }
            }
        ],
        "rootL": {
            "x": -0.16494393348693848,
            "y": 0.6201443076133728,
            "z": 0.1866244077682495
        },
        "rootR": {
            "x": 0.12315917015075684,
            "y": 1.003383994102478,
            "z": 0.44255298376083374
        },
        "RighthandRotation": {
            "x": -0.3546530306339264,
            "y": -0.19669684767723083,
            "z": -0.3543614447116852,
            "w": 0.8425909280776978
        },
        "LefthandRotation": {
            "x": -0.00154709757771343,
            "y": 0.02393743395805359,
            "z": -0.22809438407421112,
            "w": -0.9733434915542603
        },
        "headPos": {
            "x": -0.01011996902525425,
            "y": 1.134383201599121,
            "z": 0.05212085694074631
        },
        "headRot": {
            "x": -0.07394454628229141,
            "y": -0.08128257095813751,
            "z": 0.01820899359881878,
            "w": 0.9937775135040283
        }
    },
    {
        "left": [
            {
                "position": {
                    "x": 0.002828842494636774,
                    "y": -0.00494718924164772,
                    "z": 0.06482050567865372
                },
                "rotation": {
                    "x": 0.0,
                    "y": 0.0,
                    "z": 0.0,
                    "w": 1.000000238418579
                }
            },
            {
                "position": {
                    "x": 0.0,
                    "y": 0.0,
                    "z": 0.0
                },
                "rotation": {
                    "x": 0.0,
                    "y": 0.0,
                    "z": 0.0,
                    "w": 1.000000238418579
                }
            },
            {
                "position": {
                    "x": 0.03086211159825325,
                    "y": -0.014898783527314663,
                    "z": 0.03391509875655174
                },
                "rotation": {
                    "x": -0.10397418588399887,
                    "y": 0.38199228048324585,
                    "z": -0.5502370595932007,
                    "w": 0.7351945042610168
                }
            },
            {
                "position": {
                    "x": 0.05284401401877403,
                    "y": -0.023595696315169334,
                    "z": 0.056236617267131805
                },
                "rotation": {
                    "x": 0.04024030268192291,
                    "y": 0.23813669383525848,
                    "z": -0.5442191958427429,
                    "w": 0.8034285306930542
                }
            },
            {
                "position": {
                    "x": 0.06429487466812134,
                    "y": -0.03453980013728142,
                    "z": 0.08608753979206085
                },
                "rotation": {
                    "x": 0.11314338445663452,
                    "y": 0.2398766726255417,
                    "z": -0.6210072040557861,
                    "w": 0.7375693321228027
                }
            },
            {
                "position": {
                    "x": 0.07046107947826385,
                    "y": -0.04518412798643112,
                    "z": 0.10741560906171799
                },
                "rotation": {
                    "x": 0.11314338445663452,
                    "y": 0.2398766726255417,
                    "z": -0.6210072040557861,
                    "w": 0.7375693321228027
                }
            },
            {
                "position": {
                    "x": 0.02014119178056717,
                    "y": -0.008912690915167332,
                    "z": 0.036156803369522095
                },
                "rotation": {
                    "x": 0.0,
                    "y": 0.0,
                    "z": 0.0,
                    "w": 1.000000238418579
                }
            },
            {
                "position": {
                    "x": 0.02355067804455757,
                    "y": -0.007316471543163061,
                    "z": 0.09599624574184418
                },
                "rotation": {
                    "x": 0.16521409153938293,
                    "y": 0.08972328901290894,
                    "z": -0.04400775954127312,
                    "w": 0.9811819791793823
                }
            },
            {
                "position": {
                    "x": 0.0296770129352808,
                    "y": -0.01991238258779049,
                    "z": 0.13124242424964905
                },
                "rotation": {
                    "x": 0.5092897415161133,
                    "y": 0.06610347330570221,
                    "z": -0.04739800840616226,
                    "w": 0.856742799282074
                }
            },
            {
                "position": {
                    "x": 0.03125648573040962,
                    "y": -0.04127348214387894,
                    "z": 0.1427260935306549
                },
                "rotation": {
                    "x": 0.6721575856208801,
                    "y": 0.027410056442022324,
                    "z": -0.056419357657432556,
                    "w": 0.7377467751502991
                }
            },
            {
                "position": {
                    "x": 0.030294595286250114,
                    "y": -0.06341581791639328,
                    "z": 0.14589640498161316
                },
                "rotation": {
                    "x": 0.6721575856208801,
                    "y": 0.027410056442022324,
                    "z": -0.056419357657432556,
                    "w": 0.7377467751502991
                }
            },
            {
                "position": {
                    "x": 0.00393177242949605,
                    "y": -0.00735121127218008,
                    "z": 0.033994339406490326
                },
                "rotation": {
                    "x": 0.0,
                    "y": 0.0,
                    "z": 0.0,
                    "w": 1.000000238418579
                }
            },
            {
                "position": {
                    "x": 0.001725901267491281,
                    "y": -0.002543162554502487,
                    "z": 0.09564664214849472
                },
                "rotation": {
                    "x": 0.08192133903503418,
                    "y": -0.003524740459397435,
                    "z": 0.00863516703248024,
                    "w": 0.9965953230857849
                }
            },
            {
                "position": {
                    "x": 0.0014850604347884655,
                    "y": -0.009555092081427574,
                    "z": 0.1379963755607605
                },
                "rotation": {
                    "x": 0.5198156237602234,
                    "y": 0.0007997470675036311,
                    "z": 0.022282131016254425,
                    "w": 0.8539878129959106
                }
            },
            {
                "position": {
                    "x": 0.0021608753595501184,
                    "y": -0.03401350975036621,
                    "z": 0.15065771341323853
                },
                "rotation": {
                    "x": 0.7343812584877014,
                    "y": -0.019077017903327942,
                    "z": 0.08609108626842499,
                    "w": 0.6729851961135864
                }
            },
            {
                "position": {
                    "x": 0.004209102597087622,
                    "y": -0.058905623853206635,
                    "z": 0.1497500091791153
                },
                "rotation": {
                    "x": 0.7343812584877014,
                    "y": -0.019077017903327942,
                    "z": 0.08609108626842499,
                    "w": 0.6729851961135864
                }
            },
            {
                "position": {
                    "x": -0.014992350712418556,
                    "y": -0.006015788298100233,
                    "z": 0.03477555140852928
                },
                "rotation": {
                    "x": 0.0,
                    "y": 0.0,
                    "z": 0.0,
                    "w": 1.000000238418579
                }
            },
            {
                "position": {
                    "x": -0.01746525429189205,
                    "y": -0.006529309321194887,
                    "z": 0.08869381248950958
                },
                "rotation": {
                    "x": -0.009930985979735851,
                    "y": -0.06261809170246124,
                    "z": 0.05035574361681938,
                    "w": 0.9967172145843506
                }
            },
            {
                "position": {
                    "x": -0.022371934726834297,
                    "y": -0.006003215909004211,
                    "z": 0.12737645208835602
                },
                "rotation": {
                    "x": 0.45841923356056213,
                    "y": -0.01781337335705757,
                    "z": 0.11507174372673035,
                    "w": 0.8810752034187317
                }
            },
            {
                "position": {
                    "x": -0.020402532070875168,
                    "y": -0.027578257024288177,
                    "z": 0.14276428520679474
                },
                "rotation": {
                    "x": 0.70972740650177,
                    "y": 0.036492105573415756,
                    "z": 0.14510612189769745,
                    "w": 0.6884039640426636
                }
            },
            {
                "position": {
                    "x": -0.014654184691607952,
                    "y": -0.051235660910606384,
                    "z": 0.14406713843345642
                },
                "rotation": {
                    "x": 0.70972740650177,
                    "y": 0.036492105573415756,
                    "z": 0.14510612189769745,
                    "w": 0.6884039640426636
                }
            },
            {
                "position": {
                    "x": -0.02299858070909977,
                    "y": -0.009419825859367847,
                    "z": 0.034073568880558014
                },
                "rotation": {
                    "x": 0.018311800435185432,
                    "y": -0.14034287631511688,
                    "z": 0.20703600347042084,
                    "w": 0.9680418968200684
                }
            },
            {
                "position": {
                    "x": -0.03505407273769379,
                    "y": -0.013691190630197525,
                    "z": 0.07789585739374161
                },
                "rotation": {
                    "x": -0.07301311194896698,
                    "y": -0.13549010455608368,
                    "z": 0.09882190078496933,
                    "w": 0.983130931854248
                }
            },
            {
                "position": {
                    "x": -0.04368157312273979,
                    "y": -0.010103510692715645,
                    "z": 0.10716086626052856
                },
                "rotation": {
                    "x": 0.34619370102882385,
                    "y": -0.0959620252251625,
                    "z": 0.2197502851486206,
                    "w": 0.9070014357566833
                }
            },
            {
                "position": {
                    "x": -0.044126879423856735,
                    "y": -0.023715630173683167,
                    "z": 0.12222952395677567
                },
                "rotation": {
                    "x": 0.6227208375930786,
                    "y": 0.02665862999856472,
                    "z": 0.2532669007778168,
                    "w": 0.739841103553772
                }
            },
            {
                "position": {
                    "x": -0.036548007279634476,
                    "y": -0.0434020534157753,
                    "z": 0.12832356989383698
                },
                "rotation": {
                    "x": 0.6227208375930786,
                    "y": 0.02665862999856472,
                    "z": 0.2532669007778168,
                    "w": 0.739841103553772
                }
            }
        ],
        "right": [
            {
                "position": {
                    "x": -0.001830136519856751,
                    "y": -0.005637296009808779,
                    "z": 0.0654749721288681
                },
                "rotation": {
                    "x": 0.0,
                    "y": 0.0,
                    "z": 0.0,
                    "w": 1.0
                }
            },
            {
                "position": {
                    "x": 0.0,
                    "y": 0.0,
                    "z": 0.0
                },
                "rotation": {
                    "x": 0.0,
                    "y": 0.0,
                    "z": 0.0,
                    "w": 1.0
                }
            },
            {
                "position": {
                    "x": -0.02686735801398754,
                    "y": -0.020419562235474586,
                    "z": 0.03653290495276451
                },
                "rotation": {
                    "x": 0.05536181479692459,
                    "y": -0.40272045135498047,
                    "z": 0.6497969627380371,
                    "w": 0.6422734260559082
                }
            },
            {
                "position": {
                    "x": -0.041347477585077286,
                    "y": -0.03974810242652893,
                    "z": 0.05830035358667374
                },
                "rotation": {
                    "x": 0.020652752369642258,
                    "y": -0.36938729882240295,
                    "z": 0.5833228230476379,
                    "w": 0.7230911254882812
                }
            },
            {
                "position": {
                    "x": -0.05858556181192398,
                    "y": -0.05532034486532211,
                    "z": 0.08284272998571396
                },
                "rotation": {
                    "x": -0.09363709390163422,
                    "y": -0.5176088809967041,
                    "z": 0.5666245818138123,
                    "w": 0.6342316269874573
                }
            },
            {
                "position": {
                    "x": -0.07809840142726898,
                    "y": -0.06592770665884018,
                    "z": 0.09347016364336014
                },
                "rotation": {
                    "x": -0.09363709390163422,
                    "y": -0.5176088809967041,
                    "z": 0.5666245818138123,
                    "w": 0.6342316269874573
                }
            },
            {
                "position": {
                    "x": -0.01814381778240204,
                    "y": -0.01167307235300541,
                    "z": 0.037465650588274
                },
                "rotation": {
                    "x": 0.0,
                    "y": 0.0,
                    "z": 0.0,
                    "w": 1.0
                }
            },
            {
                "position": {
                    "x": -0.023550700396299362,
                    "y": -0.007316445931792259,
                    "z": 0.09599617123603821
                },
                "rotation": {
                    "x": 0.04559300094842911,
                    "y": 0.02939154952764511,
                    "z": 0.030804365873336792,
                    "w": 0.9980523586273193
                }
            },
            {
                "position": {
                    "x": -0.021219024434685707,
                    "y": -0.010699479840695858,
                    "z": 0.13370031118392944
                },
                "rotation": {
                    "x": 0.12343449145555496,
                    "y": 0.03804273158311844,
                    "z": 0.002493053674697876,
                    "w": 0.9916203022003174
                }
            },
            {
                "position": {
                    "x": -0.019370395690202713,
                    "y": -0.01664441078901291,
                    "z": 0.15719303488731384
                },
                "rotation": {
                    "x": 0.07160928845405579,
                    "y": 0.06645965576171875,
                    "z": -0.00828765332698822,
                    "w": 0.9951817393302917
                }
            },
            {
                "position": {
                    "x": -0.016119113191962242,
                    "y": -0.0188441164791584,
                    "z": 0.17923504114151
                },
                "rotation": {
                    "x": 0.07160928845405579,
                    "y": 0.06645965576171875,
                    "z": -0.00828765332698822,
                    "w": 0.9951817393302917
                }
            },
            {
                "position": {
                    "x": -0.0019343980820849538,
                    "y": -0.008731423877179623,
                    "z": 0.03530319035053253
                },
                "rotation": {
                    "x": 0.0,
                    "y": 0.0,
                    "z": 0.0,
                    "w": 1.0
                }
            },
            {
                "position": {
                    "x": -0.0017259018495678902,
                    "y": -0.0025431648828089237,
                    "z": 0.09564664214849472
                },
                "rotation": {
                    "x": 0.5715299248695374,
                    "y": 0.06428113579750061,
                    "z": -0.04833245277404785,
                    "w": 0.816630482673645
                }
            },
            {
                "position": {
                    "x": 0.0004093345196451992,
                    "y": -0.04288042336702347,
                    "z": 0.11017494648694992
                },
                "rotation": {
                    "x": 0.9858251810073853,
                    "y": 0.011318638920783997,
                    "z": -0.09306840598583221,
                    "w": 0.13913649320602417
                }
            },
            {
                "position": {
                    "x": -0.004559211898595095,
                    "y": -0.05049610137939453,
                    "z": 0.08416925370693207
                },
                "rotation": {
                    "x": 0.9081087112426758,
                    "y": 0.045133769512176514,
                    "z": -0.11909250915050507,
                    "w": -0.3988967537879944
                }
            },
            {
                "position": {
                    "x": -0.010574178770184517,
                    "y": -0.033393919467926025,
                    "z": 0.06696546822786331
                },
                "rotation": {
                    "x": 0.9081087112426758,
                    "y": 0.045133769512176514,
                    "z": -0.11909250915050507,
                    "w": -0.3988967537879944
                }
            },
            {
                "position": {
                    "x": 0.01499234326183796,
                    "y": -0.00601577665656805,
                    "z": 0.034775588661432266
                },
                "rotation": {
                    "x": 0.0,
                    "y": 0.0,
                    "z": 0.0,
                    "w": 1.0
                }
            },
            {
                "position": {
                    "x": 0.017465243116021156,
                    "y": -0.006529313046485186,
                    "z": 0.0886937826871872
                },
                "rotation": {
                    "x": 0.6653897762298584,
                    "y": 0.045679327100515366,
                    "z": -0.10073509067296982,
                    "w": 0.7382562756538391
                }
            },
            {
                "position": {
                    "x": 0.014867706224322319,
                    "y": -0.0452001579105854,
                    "z": 0.09299662709236145
                },
                "rotation": {
                    "x": 0.9858046770095825,
                    "y": -0.0239383727312088,
                    "z": -0.14904479682445526,
                    "w": 0.07349753379821777
                }
            },
            {
                "position": {
                    "x": 0.0069653806276619434,
                    "y": -0.048861242830753326,
                    "z": 0.06789092719554901
                },
                "rotation": {
                    "x": 0.8793162703514099,
                    "y": -0.07139794528484344,
                    "z": -0.1446579396724701,
                    "w": -0.4480845630168915
                }
            },
            {
                "position": {
                    "x": 0.0021674095187336206,
                    "y": -0.030134329572319984,
                    "z": 0.05303514748811722
                },
                "rotation": {
                    "x": 0.8793162703514099,
                    "y": -0.07139794528484344,
                    "z": -0.1446579396724701,
                    "w": -0.4480845630168915
                }
            },
            {
                "position": {
                    "x": 0.022998575121164322,
                    "y": -0.009419831447303295,
                    "z": 0.03407357633113861
                },
                "rotation": {
                    "x": 0.01831180602312088,
                    "y": 0.1403428614139557,
                    "z": -0.20703594386577606,
                    "w": 0.9680416584014893
                }
            },
            {
                "position": {
                    "x": 0.03505405783653259,
                    "y": -0.013691181316971779,
                    "z": 0.07789580523967743
                },
                "rotation": {
                    "x": 0.6926763653755188,
                    "y": -0.007540741469711065,
                    "z": -0.18709474802017212,
                    "w": 0.6965186595916748
                }
            },
            {
                "position": {
                    "x": 0.026768883690238,
                    "y": -0.04324737563729286,
                    "z": 0.07913345843553543
                },
                "rotation": {
                    "x": 0.9783421158790588,
                    "y": -0.06459041684865952,
                    "z": -0.19102001190185547,
                    "w": 0.046758562326431274
                }
            },
            {
                "position": {
                    "x": 0.019054478034377098,
                    "y": -0.04460449516773224,
                    "z": 0.06039309501647949
                },
                "rotation": {
                    "x": 0.8773009777069092,
                    "y": -0.15055127441883087,
                    "z": -0.18055088818073273,
                    "w": -0.4184243977069855
                }
            },
            {
                "position": {
                    "x": 0.014147328212857246,
                    "y": -0.02802523784339428,
                    "z": 0.046858739107847214
                },
                "rotation": {
                    "x": 0.8773009777069092,
                    "y": -0.15055127441883087,
                    "z": -0.18055088818073273,
                    "w": -0.4184243977069855
                }
            }
        ],
        "rootL": {
            "x": -0.17389965057373047,
            "y": 0.607778787612915,
            "z": 0.18893367052078247
        },
        "rootR": {
            "x": -0.0005669593811035156,
            "y": 1.1866501569747925,
            "z": 0.334966242313385
        },
        "RighthandRotation": {
            "x": -0.6972599625587463,
            "y": -0.3311242461204529,
            "z": -0.1759876012802124,
            "w": 0.6109121441841125
        },
        "LefthandRotation": {
            "x": -0.000977321295067668,
            "y": -0.008739233016967773,
            "z": -0.20230834186077118,
            "w": -0.9792824983596802
        },
        "headPos": {
            "x": -0.0006200280040502548,
            "y": 1.133568525314331,
            "z": -0.002463075565174222
        },
        "headRot": {
            "x": -0.08834932744503021,
            "y": -0.08220230042934418,
            "z": 0.007014645263552666,
            "w": 0.9926670789718628
        }
    },
    {
        "left": [
            {
                "position": {
                    "x": 0.002678551943972707,
                    "y": -0.0050862436182796955,
                    "z": 0.06495720148086548
                },
                "rotation": {
                    "x": 0.0,
                    "y": 0.0,
                    "z": 0.0,
                    "w": 1.0
                }
            },
            {
                "position": {
                    "x": 0.0,
                    "y": 0.0,
                    "z": 0.0
                },
                "rotation": {
                    "x": 0.0,
                    "y": 0.0,
                    "z": 0.0,
                    "w": 1.0
                }
            },
            {
                "position": {
                    "x": 0.030260998755693436,
                    "y": -0.016010960564017296,
                    "z": 0.03446207195520401
                },
                "rotation": {
                    "x": -0.10356619209051132,
                    "y": 0.3495769798755646,
                    "z": -0.563951313495636,
                    "w": 0.7409650683403015
                }
            },
            {
                "position": {
                    "x": 0.050902169197797775,
                    "y": -0.02384044975042343,
                    "z": 0.05833110213279724
                },
                "rotation": {
                    "x": 0.010359358042478561,
                    "y": 0.22269873321056366,
                    "z": -0.5415561199188232,
                    "w": 0.8105646967887878
                }
            },
            {
                "position": {
                    "x": 0.06272309273481369,
                    "y": -0.032559122890233994,
                    "z": 0.08876504749059677
                },
                "rotation": {
                    "x": 0.058000754565000534,
                    "y": 0.24475368857383728,
                    "z": -0.6132798790931702,
                    "w": 0.7487454414367676
                }
            },
            {
                "position": {
                    "x": 0.07087311148643494,
                    "y": -0.04123305156826973,
                    "z": 0.11031845211982727
                },
                "rotation": {
                    "x": 0.058000754565000534,
                    "y": 0.24475368857383728,
                    "z": -0.6132798790931702,
                    "w": 0.7487454414367676
                }
            },
            {
                "position": {
                    "x": 0.019840635359287262,
                    "y": -0.009468787349760532,
                    "z": 0.036430276930332184
                },
                "rotation": {
                    "x": 0.0,
                    "y": 0.0,
                    "z": 0.0,
                    "w": 1.0
                }
            },
            {
                "position": {
                    "x": 0.023550670593976974,
                    "y": -0.007316464092582464,
                    "z": 0.09599623829126358
                },
                "rotation": {
                    "x": 0.17965152859687805,
                    "y": 0.05047667771577835,
                    "z": -0.04112744331359863,
                    "w": 0.981573224067688
                }
            },
            {
                "position": {
                    "x": 0.026748543605208397,
                    "y": -0.020850220695137978,
                    "z": 0.13128206133842468
                },
                "rotation": {
                    "x": 0.5249254107475281,
                    "y": 0.030050624161958694,
                    "z": -0.030669022351503372,
                    "w": 0.8500645160675049
                }
            },
            {
                "position": {
                    "x": 0.02720770798623562,
                    "y": -0.042584583163261414,
                    "z": 0.14214828610420227
                },
                "rotation": {
                    "x": 0.6837892532348633,
                    "y": -0.0045583248138427734,
                    "z": -0.03317062556743622,
                    "w": 0.7289109826087952
                }
            },
            {
                "position": {
                    "x": 0.025792846456170082,
                    "y": -0.06479022651910782,
                    "z": 0.1446315348148346
                },
                "rotation": {
                    "x": 0.6837892532348633,
                    "y": -0.0045583248138427734,
                    "z": -0.03317062556743622,
                    "w": 0.7289109826087952
                }
            },
            {
                "position": {
                    "x": 0.0036312039010226727,
                    "y": -0.007629298605024815,
                    "z": 0.03426780924201012
                },
                "rotation": {
                    "x": 0.0,
                    "y": 0.0,
                    "z": 0.0,
                    "w": 1.0
                }
            },
            {
                "position": {
                    "x": 0.00172591139562428,
                    "y": -0.0025431334506720304,
                    "z": 0.09564660489559174
                },
                "rotation": {
                    "x": 0.1288653463125229,
                    "y": -0.014182452112436295,
                    "z": 0.009489309042692184,
                    "w": 0.9915152192115784
                }
            },
            {
                "position": {
                    "x": 0.0006235995097085834,
                    "y": -0.013524448499083519,
                    "z": 0.13713061809539795
                },
                "rotation": {
                    "x": 0.5444880127906799,
                    "y": -0.009431002661585808,
                    "z": 0.02761504054069519,
                    "w": 0.8382608294487
                }
            },
            {
                "position": {
                    "x": 0.0010164760751649737,
                    "y": -0.03868730366230011,
                    "z": 0.14834019541740417
                },
                "rotation": {
                    "x": 0.7399245500564575,
                    "y": -0.029678067192435265,
                    "z": 0.09137940406799316,
                    "w": 0.6657935380935669
                }
            },
            {
                "position": {
                    "x": 0.0029145709704607725,
                    "y": -0.0635710135102272,
                    "z": 0.14698559045791626
                },
                "rotation": {
                    "x": 0.7399245500564575,
                    "y": -0.029678067192435265,
                    "z": 0.09137940406799316,
                    "w": 0.6657935380935669
                }
            },
            {
                "position": {
                    "x": -0.01499234326183796,
                    "y": -0.006015796680003405,
                    "z": 0.03477552905678749
                },
                "rotation": {
                    "x": 0.0,
                    "y": 0.0,
                    "z": 0.0,
                    "w": 1.0
                }
            },
            {
                "position": {
                    "x": -0.017465239390730858,
                    "y": -0.006529316771775484,
                    "z": 0.08869380503892899
                },
                "rotation": {
                    "x": 0.031410470604896545,
                    "y": -0.06442616134881973,
                    "z": 0.05247333645820618,
                    "w": 0.9960469007492065
                }
            },
            {
                "position": {
                    "x": -0.022341568022966385,
                    "y": -0.009233037009835243,
                    "z": 0.12728922069072723
                },
                "rotation": {
                    "x": 0.5035197734832764,
                    "y": -0.018986783921718597,
                    "z": 0.1187184602022171,
                    "w": 0.8555778861045837
                }
            },
            {
                "position": {
                    "x": -0.020027965307235718,
                    "y": -0.032248493283987045,
                    "z": 0.14036904275417328
                },
                "rotation": {
                    "x": 0.7343963980674744,
                    "y": 0.03351941704750061,
                    "z": 0.1495254635810852,
                    "w": 0.6611968278884888
                }
            },
            {
                "position": {
                    "x": -0.014091752469539642,
                    "y": -0.05589138716459274,
                    "z": 0.13993321359157562
                },
                "rotation": {
                    "x": 0.7343963980674744,
                    "y": 0.03351941704750061,
                    "z": 0.1495254635810852,
                    "w": 0.6611968278884888
                }
            },
            {
                "position": {
                    "x": -0.022998584434390068,
                    "y": -0.009419858455657959,
                    "z": 0.03407354652881622
                },
                "rotation": {
                    "x": 0.01831180974841118,
                    "y": -0.1403428614139557,
                    "z": 0.20703594386577606,
                    "w": 0.9680416584014893
                }
            },
            {
                "position": {
                    "x": -0.03505408391356468,
                    "y": -0.013691187836229801,
                    "z": 0.07789582759141922
                },
                "rotation": {
                    "x": -0.04005102068185806,
                    "y": -0.11488129943609238,
                    "z": 0.10725031048059464,
                    "w": 0.986760139465332
                }
            },
            {
                "position": {
                    "x": -0.04228292033076286,
                    "y": -0.012020014226436615,
                    "z": 0.10770685225725174
                },
                "rotation": {
                    "x": 0.4183838963508606,
                    "y": -0.06726067513227463,
                    "z": 0.2230607569217682,
                    "w": 0.8778809309005737
                }
            },
            {
                "position": {
                    "x": -0.040890466421842575,
                    "y": -0.02754988893866539,
                    "z": 0.12072359770536423
                },
                "rotation": {
                    "x": 0.6667066812515259,
                    "y": 0.04920072481036186,
                    "z": 0.2504170835018158,
                    "w": 0.7002663016319275
                }
            },
            {
                "position": {
                    "x": -0.03219211474061012,
                    "y": -0.04739450290799141,
                    "z": 0.12428177148103714
                },
                "rotation": {
                    "x": 0.6667066812515259,
                    "y": 0.04920072481036186,
                    "z": 0.2504170835018158,
                    "w": 0.7002663016319275
                }
            }
        ],
        "right": [
            {
                "position": {
                    "x": -0.0010198266245424747,
                    "y": -0.005977865774184465,
                    "z": 0.0657673105597496
                },
                "rotation": {
                    "x": 0.0,
                    "y": 0.0,
                    "z": 0.0,
                    "w": 0.9999998807907104
                }
            },
            {
                "position": {
                    "x": 0.0,
                    "y": 0.0,
                    "z": 0.0
                },
                "rotation": {
                    "x": 0.0,
                    "y": 0.0,
                    "z": 0.0,
                    "w": 0.9999998807907104
                }
            },
            {
                "position": {
                    "x": -0.02362602949142456,
                    "y": -0.02314428985118866,
                    "z": 0.03770258277654648
                },
                "rotation": {
                    "x": 0.04102155566215515,
                    "y": -0.29483988881111145,
                    "z": 0.6977171301841736,
                    "w": 0.6515963077545166
                }
            },
            {
                "position": {
                    "x": -0.03425745666027069,
                    "y": -0.03825914114713669,
                    "z": 0.0644533634185791
                },
                "rotation": {
                    "x": 0.26199501752853394,
                    "y": -0.005815714597702026,
                    "z": 0.7040435671806335,
                    "w": 0.6600361466407776
                }
            },
            {
                "position": {
                    "x": -0.02205021306872368,
                    "y": -0.050223302096128464,
                    "z": 0.09360501915216446
                },
                "rotation": {
                    "x": 0.4481830894947052,
                    "y": 0.13240760564804077,
                    "z": 0.7180720567703247,
                    "w": 0.5157254934310913
                }
            },
            {
                "position": {
                    "x": -0.0035470377188175917,
                    "y": -0.05678357928991318,
                    "z": 0.10846452414989471
                },
                "rotation": {
                    "x": 0.4481830894947052,
                    "y": 0.13240760564804077,
                    "z": 0.7180720567703247,
                    "w": 0.5157254934310913
                }
            },
            {
                "position": {
                    "x": -0.016523156315088272,
                    "y": -0.013035421259701252,
                    "z": 0.0380505733191967
                },
                "rotation": {
                    "x": 0.0,
                    "y": 0.0,
                    "z": 0.0,
                    "w": 0.9999998807907104
                }
            },
            {
                "position": {
                    "x": -0.023550672456622124,
                    "y": -0.007316441275179386,
                    "z": 0.09599624574184418
                },
                "rotation": {
                    "x": 0.17823410034179688,
                    "y": 0.009475506842136383,
                    "z": 0.03371191769838333,
                    "w": 0.9833647608757019
                }
            },
            {
                "position": {
                    "x": -0.022388091310858727,
                    "y": -0.020587172359228134,
                    "z": 0.1315070241689682
                },
                "rotation": {
                    "x": 0.23348098993301392,
                    "y": 0.02164945751428604,
                    "z": 0.00846903771162033,
                    "w": 0.9720833897590637
                }
            },
            {
                "position": {
                    "x": -0.021269045770168304,
                    "y": -0.031610310077667236,
                    "z": 0.1531381756067276
                },
                "rotation": {
                    "x": 0.19349686801433563,
                    "y": 0.05100023001432419,
                    "z": -0.00023149698972702026,
                    "w": 0.979774534702301
                }
            },
            {
                "position": {
                    "x": -0.018721332773566246,
                    "y": -0.039136286824941635,
                    "z": 0.17406964302062988
                },
                "rotation": {
                    "x": 0.19349686801433563,
                    "y": 0.05100023001432419,
                    "z": -0.00023149698972702026,
                    "w": 0.979774534702301
                }
            },
            {
                "position": {
                    "x": -0.00031373227830044925,
                    "y": -0.009412599727511406,
                    "z": 0.03588804230093956
                },
                "rotation": {
                    "x": 0.0,
                    "y": 0.0,
                    "z": 0.0,
                    "w": 0.9999998807907104
                }
            },
            {
                "position": {
                    "x": -0.0017259027808904648,
                    "y": -0.0025431527756154537,
                    "z": 0.09564656764268875
                },
                "rotation": {
                    "x": 0.5775066614151001,
                    "y": 0.07015251368284225,
                    "z": -0.052841730415821075,
                    "w": 0.8116478323936462
                }
            },
            {
                "position": {
                    "x": 0.0005425806739367545,
                    "y": -0.043103933334350586,
                    "z": 0.10951756685972214
                },
                "rotation": {
                    "x": 0.9804293513298035,
                    "y": 0.01587618887424469,
                    "z": -0.09985946863889694,
                    "w": 0.16892118752002716
                }
            },
            {
                "position": {
                    "x": -0.0047041322104632854,
                    "y": -0.05231654644012451,
                    "z": 0.08408967405557632
                },
                "rotation": {
                    "x": 0.9080135822296143,
                    "y": 0.043283358216285706,
                    "z": -0.12990017235279083,
                    "w": -0.3959341049194336
                }
            },
            {
                "position": {
                    "x": -0.01117960549890995,
                    "y": -0.035367269068956375,
                    "z": 0.06690170615911484
                },
                "rotation": {
                    "x": 0.9080135822296143,
                    "y": 0.043283358216285706,
                    "z": -0.12990017235279083,
                    "w": -0.3959341049194336
                }
            },
            {
                "position": {
                    "x": 0.014992328360676765,
                    "y": -0.006015770137310028,
                    "z": 0.03477557376027107
                },
                "rotation": {
                    "x": 0.0,
                    "y": 0.0,
                    "z": 0.0,
                    "w": 0.9999998807907104
                }
            },
            {
                "position": {
                    "x": 0.01746523007750511,
                    "y": -0.0065292902290821075,
                    "z": 0.08869383484125137
                },
                "rotation": {
                    "x": 0.6618103981018066,
                    "y": 0.05072135478258133,
                    "z": -0.10420385003089905,
                    "w": 0.7406590580940247
                }
            },
            {
                "position": {
                    "x": 0.01501659769564867,
                    "y": -0.04517141729593277,
                    "z": 0.09332918375730515
                },
                "rotation": {
                    "x": 0.9815332293510437,
                    "y": -0.01854846253991127,
                    "z": -0.15565499663352966,
                    "w": 0.10963557660579681
                }
            },
            {
                "position": {
                    "x": 0.006788726896047592,
                    "y": -0.050737131386995316,
                    "z": 0.06868235021829605
                },
                "rotation": {
                    "x": 0.8812887072563171,
                    "y": -0.07380825281143188,
                    "z": -0.1508549451828003,
                    "w": -0.4417297840118408
                }
            },
            {
                "position": {
                    "x": 0.0017266040667891502,
                    "y": -0.032217759639024734,
                    "z": 0.05365503206849098
                },
                "rotation": {
                    "x": 0.8812887072563171,
                    "y": -0.07380825281143188,
                    "z": -0.1508549451828003,
                    "w": -0.4417297840118408
                }
            },
            {
                "position": {
                    "x": 0.022998567670583725,
                    "y": -0.009419827722012997,
                    "z": 0.03407354652881622
                },
                "rotation": {
                    "x": 0.018311813473701477,
                    "y": 0.1403428316116333,
                    "z": -0.20703594386577606,
                    "w": 0.9680415987968445
                }
            },
            {
                "position": {
                    "x": 0.03505407273769379,
                    "y": -0.013691181316971779,
                    "z": 0.07789583504199982
                },
                "rotation": {
                    "x": 0.662106990814209,
                    "y": -0.006233349442481995,
                    "z": -0.181647390127182,
                    "w": 0.7270347476005554
                }
            },
            {
                "position": {
                    "x": 0.027386121451854706,
                    "y": -0.043197669088840485,
                    "z": 0.08167911320924759
                },
                "rotation": {
                    "x": 0.9739172458648682,
                    "y": -0.06016920879483223,
                    "z": -0.19155411422252655,
                    "w": 0.10569634288549423
                }
            },
            {
                "position": {
                    "x": 0.019549284130334854,
                    "y": -0.046911150217056274,
                    "z": 0.06331215053796768
                },
                "rotation": {
                    "x": 0.8491616249084473,
                    "y": -0.1659533828496933,
                    "z": -0.16055512428283691,
                    "w": -0.4749801754951477
                }
            },
            {
                "position": {
                    "x": 0.016279231756925583,
                    "y": -0.028627322986721992,
                    "z": 0.05160151422023773
                },
                "rotation": {
                    "x": 0.8491616249084473,
                    "y": -0.1659533828496933,
                    "z": -0.16055512428283691,
                    "w": -0.4749801754951477
                }
            }
        ],
        "rootL": {
            "x": -0.1764523983001709,
            "y": 0.6063161492347717,
            "z": 0.18532580137252808
        },
        "rootR": {
            "x": 0.10074949264526367,
            "y": 1.143822193145752,
            "z": 0.38343173265457153
        },
        "RighthandRotation": {
            "x": -0.6314777731895447,
            "y": -0.20149171352386475,
            "z": -0.24633680284023285,
            "w": 0.7070749402046204
        },
        "LefthandRotation": {
            "x": 0.03602387383580208,
            "y": -0.03740110993385315,
            "z": -0.22749371826648712,
            "w": -0.9723939895629883
        },
        "headPos": {
            "x": -0.001325269229710102,
            "y": 1.126498818397522,
            "z": 0.029302475973963737
        },
        "headRot": {
            "x": -0.046547651290893555,
            "y": -0.05528037250041962,
            "z": 0.011517828330397606,
            "w": 0.9973188042640686
        }
    }
]